{"team":"Bahrain","flag":"🇧🇭","confederation":"Asia/Oceania","seasons":{"2011":[{"date":"2011-09-15","rating":-17.834,"rank":null,"conf_rank":null,"last_match":"L 49-101 vs. China (FIBA Asia Cup)","is_end_of_season":0,"is_game_day":1,"is_year_anchor":0,"year_anchor_label":"","tournament_finishes":[],"continental_winner":0},{"date":"2011-09-16","rating":-33.743,"rank":null,"conf_rank":null,"last_match":"L 53-91 vs. United Arab Emirates (FIBA Asia Cup)","is_end_of_season":0,"is_game_day":1,"is_year_anchor":0,"year_anchor_label":"","tournament_finishes":[],"continental_winner":0},{"date":"2011-09-17","rating":-31.8,"rank":null,"conf_rank":null,"last_match":"L 71-113 vs. Philippines (FIBA Asia Cup)","is_end_of_season":0,"is_game_day":1,"is_year_anchor":0,"year_anchor_label":"","tournament_finishes":[],"continental_winner":0},{"date":"2011-09-18","rating":-31.797,"rank":null,"conf_rank":null,"last_match":"L 71-113 vs. Philippines (FIBA Asia Cup)","is_end_of_season":1,"is_game_day":1,"is_year_anchor":0,"year_anchor_label":"","tournament_finishes":[],"continental_winner":0},{"date":"2011-09-19","rating":-35.545,"rank":77,"conf_rank":21,"last_match":"L 62-85 vs. Indonesia (FIBA Asia Cup)","is_end_of_season":0,"is_game_day":1,"is_year_anchor":0,"year_anchor_label":"","tournament_finishes":[],"continental_winner":0},{"date":"2011-09-20","rating":-26.339,"rank":74,"conf_rank":20,"last_match":"W 20-0 vs. Qatar (FIBA Asia Cup)","is_end_of_season":0,"is_game_day":1,"is_year_anchor":0,"year_anchor_label":"","tournament_finishes":[],"continental_winner":0},{"date":"2011-09-21","rating":-26.444,"rank":75,"conf_rank":20,"last_match":"W 20-0 vs. Qatar (FIBA Asia Cup)","is_end_of_season":0,"is_game_day":1,"is_year_anchor":0,"year_anchor_label":"","tournament_finishes":[],"continental_winner":0},{"date":"2011-09-23","rating":-25.691,"rank":74,"conf_rank":20,"last_match":"W 20-0 vs. Qatar (FIBA Asia Cup)","is_end_of_season":0,"is_game_day":1,"is_year_anchor":0,"year_anchor_label":"","tournament_finishes":[],"continental_winner":0},{"date":"2011-09-24","rating":-26.203,"rank":75,"conf_rank":20,"last_match":"W 20-0 vs. Qatar (FIBA Asia Cup)","is_end_of_season":0,"is_game_day":1,"is_year_anchor":0,"year_anchor_label":"","tournament_finishes":[],"continental_winner":0},{"date":"2011-09-25","rating":-26.162,"rank":75,"conf_rank":20,"last_match":"W 20-0 vs. Qatar (FIBA Asia Cup)","is_end_of_season":1,"is_game_day":1,"is_year_anchor":1,"year_anchor_label":"End of FIBA Asia Cup","tournament_finishes":[],"continental_winner":0}],"2012":[{"date":"2012-07-29","rating":-26.167,"rank":75,"conf_rank":20,"last_match":"W 20-0 vs. Qatar (FIBA Asia Cup)","is_end_of_season":0,"is_game_day":1,"is_year_anchor":0,"year_anchor_label":"","tournament_finishes":[],"continental_winner":0},{"date":"2012-07-31","rating":-26.478,"rank":75,"conf_rank":20,"last_match":"W 20-0 vs. Qatar (FIBA Asia Cup)","is_end_of_season":0,"is_game_day":1,"is_year_anchor":0,"year_anchor_label":"","tournament_finishes":[],"continental_winner":0},{"date":"2012-08-02","rating":-27.124,"rank":76,"conf_rank":20,"last_match":"W 20-0 vs. Qatar (FIBA Asia Cup)","is_end_of_season":0,"is_game_day":1,"is_year_anchor":0,"year_anchor_label":"","tournament_finishes":[],"continental_winner":0},{"date":"2012-08-04","rating":-27.627,"rank":76,"conf_rank":20,"last_match":"W 20-0 vs. Qatar (FIBA Asia Cup)","is_end_of_season":0,"is_game_day":1,"is_year_anchor":0,"year_anchor_label":"","tournament_finishes":[],"continental_winner":0},{"date":"2012-08-06","rating":-28.55,"rank":76,"conf_rank":20,"last_match":"W 20-0 vs. Qatar (FIBA Asia Cup)","is_end_of_season":0,"is_game_day":1,"is_year_anchor":0,"year_anchor_label":"","tournament_finishes":[],"continental_winner":0},{"date":"2012-08-08","rating":-28.631,"rank":76,"conf_rank":20,"last_match":"W 20-0 vs. Qatar (FIBA Asia Cup)","is_end_of_season":0,"is_game_day":1,"is_year_anchor":0,"year_anchor_label":"","tournament_finishes":[],"continental_winner":0},{"date":"2012-08-10","rating":-28.63,"rank":76,"conf_rank":20,"last_match":"W 20-0 vs. Qatar (FIBA Asia Cup)","is_end_of_season":0,"is_game_day":1,"is_year_anchor":0,"year_anchor_label":"","tournament_finishes":[],"continental_winner":0},{"date":"2012-08-12","rating":-28.537,"rank":76,"conf_rank":20,"last_match":"W 20-0 vs. Qatar (FIBA Asia Cup)","is_end_of_season":1,"is_game_day":1,"is_year_anchor":1,"year_anchor_label":"End of year","tournament_finishes":[],"continental_winner":0}],"2013":[{"date":"2013-08-01","rating":-24.823,"rank":76,"conf_rank":20,"last_match":"W 82-80 vs. India (FIBA Asia Cup)","is_end_of_season":0,"is_game_day":1,"is_year_anchor":0,"year_anchor_label":"","tournament_finishes":[],"continental_winner":0},{"date":"2013-08-02","rating":-23.629,"rank":75,"conf_rank":20,"last_match":"L 76-79 vs. Kazakhstan (FIBA Asia Cup)","is_end_of_season":0,"is_game_day":1,"is_year_anchor":0,"year_anchor_label":"","tournament_finishes":[],"continental_winner":0},{"date":"2013-08-03","rating":-21.882,"rank":74,"conf_rank":20,"last_match":"W 86-62 vs. Thailand (FIBA Asia Cup)","is_end_of_season":0,"is_game_day":1,"is_year_anchor":0,"year_anchor_label":"","tournament_finishes":[],"continental_winner":0},{"date":"2013-08-05","rating":-19.511,"rank":69,"conf_rank":17,"last_match":"L 51-96 vs. South Korea (FIBA Asia Cup)","is_end_of_season":0,"is_game_day":1,"is_year_anchor":0,"year_anchor_label":"","tournament_finishes":[],"continental_winner":0},{"date":"2013-08-06","rating":-18.117,"rank":66,"conf_rank":15,"last_match":"L 56-75 vs. Iran (FIBA Asia Cup)","is_end_of_season":0,"is_game_day":1,"is_year_anchor":0,"year_anchor_label":"","tournament_finishes":[],"continental_winner":0},{"date":"2013-08-07","rating":-18.204,"rank":66,"conf_rank":15,"last_match":"L 66-88 vs. China (FIBA Asia Cup)","is_end_of_season":0,"is_game_day":1,"is_year_anchor":0,"year_anchor_label":"","tournament_finishes":[],"continental_winner":0},{"date":"2013-08-09","rating":-17.91,"rank":66,"conf_rank":15,"last_match":"L 66-88 vs. China (FIBA Asia Cup)","is_end_of_season":0,"is_game_day":1,"is_year_anchor":0,"year_anchor_label":"","tournament_finishes":[],"continental_winner":0},{"date":"2013-08-10","rating":-18.128,"rank":66,"conf_rank":16,"last_match":"L 66-88 vs. China (FIBA Asia Cup)","is_end_of_season":0,"is_game_day":1,"is_year_anchor":0,"year_anchor_label":"","tournament_finishes":[],"continental_winner":0},{"date":"2013-08-11","rating":-19.067,"rank":68,"conf_rank":18,"last_match":"L 66-88 vs. China (FIBA Asia Cup)","is_end_of_season":1,"is_game_day":1,"is_year_anchor":1,"year_anchor_label":"End of FIBA Asia Cup","tournament_finishes":[],"continental_winner":0},{"date":"2013-08-20","rating":-18.888,"rank":68,"conf_rank":18,"last_match":"L 66-88 vs. China (FIBA Asia Cup)","is_end_of_season":0,"is_game_day":1,"is_year_anchor":0,"year_anchor_label":"","tournament_finishes":[],"continental_winner":0},{"date":"2013-08-21","rating":-18.278,"rank":68,"conf_rank":18,"last_match":"L 66-88 vs. China (FIBA Asia Cup)","is_end_of_season":0,"is_game_day":1,"is_year_anchor":0,"year_anchor_label":"","tournament_finishes":[],"continental_winner":0},{"date":"2013-08-22","rating":-17.986,"rank":68,"conf_rank":18,"last_match":"L 66-88 vs. China (FIBA Asia Cup)","is_end_of_season":0,"is_game_day":1,"is_year_anchor":0,"year_anchor_label":"","tournament_finishes":[],"continental_winner":0},{"date":"2013-08-23","rating":-18.376,"rank":68,"conf_rank":18,"last_match":"L 66-88 vs. China (FIBA Asia Cup)","is_end_of_season":0,"is_game_day":1,"is_year_anchor":0,"year_anchor_label":"","tournament_finishes":[],"continental_winner":0},{"date":"2013-08-24","rating":-18.5,"rank":68,"conf_rank":18,"last_match":"L 66-88 vs. China (FIBA Asia Cup)","is_end_of_season":0,"is_game_day":1,"is_year_anchor":0,"year_anchor_label":"","tournament_finishes":[],"continental_winner":0},{"date":"2013-08-25","rating":-18.677,"rank":68,"conf_rank":18,"last_match":"L 66-88 vs. China (FIBA Asia Cup)","is_end_of_season":0,"is_game_day":1,"is_year_anchor":0,"year_anchor_label":"","tournament_finishes":[],"continental_winner":0},{"date":"2013-08-26","rating":-18.693,"rank":68,"conf_rank":18,"last_match":"L 66-88 vs. China (FIBA Asia Cup)","is_end_of_season":0,"is_game_day":1,"is_year_anchor":0,"year_anchor_label":"","tournament_finishes":[],"continental_winner":0},{"date":"2013-08-27","rating":-18.769,"rank":70,"conf_rank":18,"last_match":"L 66-88 vs. China (FIBA Asia Cup)","is_end_of_season":0,"is_game_day":1,"is_year_anchor":0,"year_anchor_label":"","tournament_finishes":[],"continental_winner":0},{"date":"2013-08-28","rating":-18.599,"rank":70,"conf_rank":18,"last_match":"L 66-88 vs. China (FIBA Asia Cup)","is_end_of_season":0,"is_game_day":1,"is_year_anchor":0,"year_anchor_label":"","tournament_finishes":[],"continental_winner":0},{"date":"2013-08-29","rating":-18.892,"rank":70,"conf_rank":18,"last_match":"L 66-88 vs. China (FIBA Asia Cup)","is_end_of_season":0,"is_game_day":1,"is_year_anchor":0,"year_anchor_label":"","tournament_finishes":[],"continental_winner":0},{"date":"2013-08-30","rating":-18.852,"rank":70,"conf_rank":18,"last_match":"L 66-88 vs. China (FIBA Asia Cup)","is_end_of_season":0,"is_game_day":1,"is_year_anchor":0,"year_anchor_label":"","tournament_finishes":[],"continental_winner":0},{"date":"2013-08-31","rating":-18.99,"rank":70,"conf_rank":18,"last_match":"L 66-88 vs. China (FIBA Asia Cup)","is_end_of_season":1,"is_game_day":1,"is_year_anchor":0,"year_anchor_label":"","tournament_finishes":[],"continental_winner":0},{"date":"2013-09-01","rating":-19.285,"rank":70,"conf_rank":18,"last_match":"L 66-88 vs. China (FIBA Asia Cup)","is_end_of_season":0,"is_game_day":1,"is_year_anchor":0,"year_anchor_label":"","tournament_finishes":[],"continental_winner":0},{"date":"2013-09-02","rating":-19.7,"rank":70,"conf_rank":18,"last_match":"L 66-88 vs. China (FIBA Asia Cup)","is_end_of_season":0,"is_game_day":1,"is_year_anchor":0,"year_anchor_label":"","tournament_finishes":[],"continental_winner":0},{"date":"2013-09-03","rating":-19.655,"rank":71,"conf_rank":18,"last_match":"L 66-88 vs. China (FIBA Asia Cup)","is_end_of_season":0,"is_game_day":1,"is_year_anchor":0,"year_anchor_label":"","tournament_finishes":[],"continental_winner":0},{"date":"2013-09-05","rating":-19.522,"rank":71,"conf_rank":18,"last_match":"L 66-88 vs. China (FIBA Asia Cup)","is_end_of_season":0,"is_game_day":1,"is_year_anchor":0,"year_anchor_label":"","tournament_finishes":[],"continental_winner":0},{"date":"2013-09-06","rating":-19.65,"rank":71,"conf_rank":18,"last_match":"L 66-88 vs. China (FIBA Asia Cup)","is_end_of_season":0,"is_game_day":1,"is_year_anchor":0,"year_anchor_label":"","tournament_finishes":[],"continental_winner":0},{"date":"2013-09-07","rating":-19.651,"rank":71,"conf_rank":18,"last_match":"L 66-88 vs. China (FIBA Asia Cup)","is_end_of_season":0,"is_game_day":1,"is_year_anchor":0,"year_anchor_label":"","tournament_finishes":[],"continental_winner":0},{"date":"2013-09-08","rating":-19.673,"rank":71,"conf_rank":18,"last_match":"L 66-88 vs. China (FIBA Asia Cup)","is_end_of_season":0,"is_game_day":1,"is_year_anchor":0,"year_anchor_label":"","tournament_finishes":[],"continental_winner":0},{"date":"2013-09-10","rating":-19.658,"rank":71,"conf_rank":18,"last_match":"L 66-88 vs. China (FIBA Asia Cup)","is_end_of_season":0,"is_game_day":1,"is_year_anchor":0,"year_anchor_label":"","tournament_finishes":[],"continental_winner":0},{"date":"2013-09-11","rating":-19.71,"rank":71,"conf_rank":18,"last_match":"L 66-88 vs. China (FIBA Asia Cup)","is_end_of_season":1,"is_game_day":1,"is_year_anchor":0,"year_anchor_label":"","tournament_finishes":[],"continental_winner":0},{"date":"2013-09-12","rating":-19.673,"rank":71,"conf_rank":18,"last_match":"L 66-88 vs. China (FIBA Asia Cup)","is_end_of_season":0,"is_game_day":1,"is_year_anchor":0,"year_anchor_label":"","tournament_finishes":[],"continental_winner":0},{"date":"2013-09-13","rating":-19.763,"rank":71,"conf_rank":18,"last_match":"L 66-88 vs. China (FIBA Asia Cup)","is_end_of_season":0,"is_game_day":1,"is_year_anchor":0,"year_anchor_label":"","tournament_finishes":[],"continental_winner":0},{"date":"2013-09-14","rating":-19.687,"rank":71,"conf_rank":18,"last_match":"L 66-88 vs. China (FIBA Asia Cup)","is_end_of_season":0,"is_game_day":1,"is_year_anchor":0,"year_anchor_label":"","tournament_finishes":[],"continental_winner":0},{"date":"2013-09-15","rating":-19.679,"rank":71,"conf_rank":18,"last_match":"L 66-88 vs. China (FIBA Asia Cup)","is_end_of_season":0,"is_game_day":1,"is_year_anchor":0,"year_anchor_label":"","tournament_finishes":[],"continental_winner":0},{"date":"2013-09-16","rating":-19.927,"rank":71,"conf_rank":18,"last_match":"L 66-88 vs. China (FIBA Asia Cup)","is_end_of_season":0,"is_game_day":1,"is_year_anchor":0,"year_anchor_label":"","tournament_finishes":[],"continental_winner":0},{"date":"2013-09-18","rating":-19.863,"rank":71,"conf_rank":18,"last_match":"L 66-88 vs. China (FIBA Asia Cup)","is_end_of_season":0,"is_game_day":1,"is_year_anchor":0,"year_anchor_label":"","tournament_finishes":[],"continental_winner":0},{"date":"2013-09-19","rating":-19.862,"rank":71,"conf_rank":18,"last_match":"L 66-88 vs. China (FIBA Asia Cup)","is_end_of_season":0,"is_game_day":1,"is_year_anchor":0,"year_anchor_label":"","tournament_finishes":[],"continental_winner":0},{"date":"2013-09-20","rating":-19.943,"rank":71,"conf_rank":18,"last_match":"L 66-88 vs. China (FIBA Asia Cup)","is_end_of_season":0,"is_game_day":1,"is_year_anchor":0,"year_anchor_label":"","tournament_finishes":[],"continental_winner":0},{"date":"2013-09-21","rating":-19.926,"rank":71,"conf_rank":18,"last_match":"L 66-88 vs. China (FIBA Asia Cup)","is_end_of_season":0,"is_game_day":1,"is_year_anchor":0,"year_anchor_label":"","tournament_finishes":[],"continental_winner":0},{"date":"2013-09-22","rating":-19.85,"rank":71,"conf_rank":18,"last_match":"L 66-88 vs. China (FIBA Asia Cup)","is_end_of_season":1,"is_game_day":1,"is_year_anchor":0,"year_anchor_label":"","tournament_finishes":[],"continental_winner":0}],"2014":[{"date":"2014-08-01","rating":-19.449,"rank":69,"conf_rank":16,"last_match":"L 66-88 vs. China (FIBA Asia Cup)","is_end_of_season":0,"is_game_day":1,"is_year_anchor":0,"year_anchor_label":"","tournament_finishes":[],"continental_winner":0},{"date":"2014-08-30","rating":-21.204,"rank":70,"conf_rank":16,"last_match":"L 66-88 vs. China (FIBA Asia Cup)","is_end_of_season":0,"is_game_day":1,"is_year_anchor":0,"year_anchor_label":"","tournament_finishes":[],"continental_winner":0},{"date":"2014-08-31","rating":-23.116,"rank":72,"conf_rank":16,"last_match":"L 66-88 vs. China (FIBA Asia Cup)","is_end_of_season":0,"is_game_day":1,"is_year_anchor":0,"year_anchor_label":"","tournament_finishes":[],"continental_winner":0},{"date":"2014-09-01","rating":-23.094,"rank":72,"conf_rank":16,"last_match":"L 66-88 vs. China (FIBA Asia Cup)","is_end_of_season":0,"is_game_day":1,"is_year_anchor":0,"year_anchor_label":"","tournament_finishes":[],"continental_winner":0},{"date":"2014-09-02","rating":-23.037,"rank":72,"conf_rank":16,"last_match":"L 66-88 vs. China (FIBA Asia Cup)","is_end_of_season":0,"is_game_day":1,"is_year_anchor":0,"year_anchor_label":"","tournament_finishes":[],"continental_winner":0},{"date":"2014-09-03","rating":-22.381,"rank":70,"conf_rank":16,"last_match":"L 66-88 vs. China (FIBA Asia Cup)","is_end_of_season":0,"is_game_day":1,"is_year_anchor":0,"year_anchor_label":"","tournament_finishes":[],"continental_winner":0},{"date":"2014-09-04","rating":-22.352,"rank":72,"conf_rank":16,"last_match":"L 66-88 vs. China (FIBA Asia Cup)","is_end_of_season":0,"is_game_day":1,"is_year_anchor":0,"year_anchor_label":"","tournament_finishes":[],"continental_winner":0},{"date":"2014-09-06","rating":-22.281,"rank":71,"conf_rank":16,"last_match":"L 66-88 vs. China (FIBA Asia Cup)","is_end_of_season":0,"is_game_day":1,"is_year_anchor":0,"year_anchor_label":"","tournament_finishes":[],"continental_winner":0},{"date":"2014-09-07","rating":-22.27,"rank":71,"conf_rank":16,"last_match":"L 66-88 vs. China (FIBA Asia Cup)","is_end_of_season":0,"is_game_day":1,"is_year_anchor":0,"year_anchor_label":"","tournament_finishes":[],"continental_winner":0},{"date":"2014-09-09","rating":-22.209,"rank":71,"conf_rank":16,"last_match":"L 66-88 vs. China (FIBA Asia Cup)","is_end_of_season":0,"is_game_day":1,"is_year_anchor":0,"year_anchor_label":"","tournament_finishes":[],"continental_winner":0},{"date":"2014-09-10","rating":-22.326,"rank":72,"conf_rank":16,"last_match":"L 66-88 vs. China (FIBA Asia Cup)","is_end_of_season":1,"is_game_day":1,"is_year_anchor":1,"year_anchor_label":"End of year","tournament_finishes":[],"continental_winner":0}],"2015":[{"date":"2015-08-19","rating":-21.684,"rank":69,"conf_rank":16,"last_match":"L 66-88 vs. China (FIBA Asia Cup)","is_end_of_season":0,"is_game_day":1,"is_year_anchor":0,"year_anchor_label":"","tournament_finishes":[],"continental_winner":0},{"date":"2015-08-20","rating":-21.497,"rank":68,"conf_rank":16,"last_match":"L 66-88 vs. China (FIBA Asia Cup)","is_end_of_season":0,"is_game_day":1,"is_year_anchor":0,"year_anchor_label":"","tournament_finishes":[],"continental_winner":0},{"date":"2015-08-21","rating":-21.132,"rank":68,"conf_rank":16,"last_match":"L 66-88 vs. China (FIBA Asia Cup)","is_end_of_season":0,"is_game_day":1,"is_year_anchor":0,"year_anchor_label":"","tournament_finishes":[],"continental_winner":0},{"date":"2015-08-22","rating":-21.488,"rank":68,"conf_rank":16,"last_match":"L 66-88 vs. China (FIBA Asia Cup)","is_end_of_season":0,"is_game_day":1,"is_year_anchor":0,"year_anchor_label":"","tournament_finishes":[],"continental_winner":0},{"date":"2015-08-23","rating":-22.033,"rank":69,"conf_rank":16,"last_match":"L 66-88 vs. China (FIBA Asia Cup)","is_end_of_season":0,"is_game_day":1,"is_year_anchor":0,"year_anchor_label":"","tournament_finishes":[],"continental_winner":0},{"date":"2015-08-24","rating":-22.539,"rank":69,"conf_rank":16,"last_match":"L 66-88 vs. China (FIBA Asia Cup)","is_end_of_season":0,"is_game_day":1,"is_year_anchor":0,"year_anchor_label":"","tournament_finishes":[],"continental_winner":0},{"date":"2015-08-25","rating":-22.587,"rank":70,"conf_rank":16,"last_match":"L 66-88 vs. China (FIBA Asia Cup)","is_end_of_season":0,"is_game_day":1,"is_year_anchor":0,"year_anchor_label":"","tournament_finishes":[],"continental_winner":0},{"date":"2015-08-26","rating":-22.568,"rank":72,"conf_rank":16,"last_match":"L 66-88 vs. China (FIBA Asia Cup)","is_end_of_season":0,"is_game_day":1,"is_year_anchor":0,"year_anchor_label":"","tournament_finishes":[],"continental_winner":0},{"date":"2015-08-27","rating":-22.537,"rank":71,"conf_rank":16,"last_match":"L 66-88 vs. China (FIBA Asia Cup)","is_end_of_season":0,"is_game_day":1,"is_year_anchor":0,"year_anchor_label":"","tournament_finishes":[],"continental_winner":0},{"date":"2015-08-28","rating":-22.337,"rank":70,"conf_rank":16,"last_match":"L 66-88 vs. China (FIBA Asia Cup)","is_end_of_season":0,"is_game_day":1,"is_year_anchor":0,"year_anchor_label":"","tournament_finishes":[],"continental_winner":0},{"date":"2015-08-29","rating":-22.351,"rank":70,"conf_rank":16,"last_match":"L 66-88 vs. China (FIBA Asia Cup)","is_end_of_season":0,"is_game_day":1,"is_year_anchor":0,"year_anchor_label":"","tournament_finishes":[],"continental_winner":0},{"date":"2015-08-30","rating":-22.501,"rank":69,"conf_rank":16,"last_match":"L 66-88 vs. China (FIBA Asia Cup)","is_end_of_season":1,"is_game_day":1,"is_year_anchor":0,"year_anchor_label":"","tournament_finishes":[],"continental_winner":0},{"date":"2015-08-31","rating":-22.583,"rank":70,"conf_rank":16,"last_match":"L 66-88 vs. China (FIBA Asia Cup)","is_end_of_season":0,"is_game_day":1,"is_year_anchor":0,"year_anchor_label":"","tournament_finishes":[],"continental_winner":0},{"date":"2015-09-01","rating":-22.577,"rank":64,"conf_rank":16,"last_match":"L 66-88 vs. China (FIBA Asia Cup)","is_end_of_season":0,"is_game_day":1,"is_year_anchor":0,"year_anchor_label":"","tournament_finishes":[],"continental_winner":0},{"date":"2015-09-02","rating":-22.675,"rank":64,"conf_rank":16,"last_match":"L 66-88 vs. China (FIBA Asia Cup)","is_end_of_season":0,"is_game_day":1,"is_year_anchor":0,"year_anchor_label":"","tournament_finishes":[],"continental_winner":0},{"date":"2015-09-03","rating":-22.849,"rank":64,"conf_rank":16,"last_match":"L 66-88 vs. China (FIBA Asia Cup)","is_end_of_season":0,"is_game_day":1,"is_year_anchor":0,"year_anchor_label":"","tournament_finishes":[],"continental_winner":0},{"date":"2015-09-04","rating":-22.824,"rank":64,"conf_rank":16,"last_match":"L 66-88 vs. China (FIBA Asia Cup)","is_end_of_season":0,"is_game_day":1,"is_year_anchor":0,"year_anchor_label":"","tournament_finishes":[],"continental_winner":0},{"date":"2015-09-05","rating":-22.722,"rank":64,"conf_rank":16,"last_match":"L 66-88 vs. China (FIBA Asia Cup)","is_end_of_season":0,"is_game_day":1,"is_year_anchor":0,"year_anchor_label":"","tournament_finishes":[],"continental_winner":0},{"date":"2015-09-06","rating":-22.91,"rank":64,"conf_rank":16,"last_match":"L 66-88 vs. China (FIBA Asia Cup)","is_end_of_season":0,"is_game_day":1,"is_year_anchor":0,"year_anchor_label":"","tournament_finishes":[],"continental_winner":0},{"date":"2015-09-07","rating":-23.209,"rank":65,"conf_rank":16,"last_match":"L 66-88 vs. China (FIBA Asia Cup)","is_end_of_season":0,"is_game_day":1,"is_year_anchor":0,"year_anchor_label":"","tournament_finishes":[],"continental_winner":0},{"date":"2015-09-08","rating":-23.296,"rank":65,"conf_rank":16,"last_match":"L 66-88 vs. China (FIBA Asia Cup)","is_end_of_season":0,"is_game_day":1,"is_year_anchor":0,"year_anchor_label":"","tournament_finishes":[],"continental_winner":0},{"date":"2015-09-09","rating":-23.258,"rank":72,"conf_rank":16,"last_match":"L 66-88 vs. China (FIBA Asia Cup)","is_end_of_season":0,"is_game_day":1,"is_year_anchor":0,"year_anchor_label":"","tournament_finishes":[],"continental_winner":0},{"date":"2015-09-10","rating":-23.219,"rank":72,"conf_rank":16,"last_match":"L 66-88 vs. China (FIBA Asia Cup)","is_end_of_season":0,"is_game_day":1,"is_year_anchor":0,"year_anchor_label":"","tournament_finishes":[],"continental_winner":0},{"date":"2015-09-11","rating":-23.232,"rank":72,"conf_rank":16,"last_match":"L 66-88 vs. China (FIBA Asia Cup)","is_end_of_season":0,"is_game_day":1,"is_year_anchor":0,"year_anchor_label":"","tournament_finishes":[],"continental_winner":0},{"date":"2015-09-12","rating":-23.119,"rank":72,"conf_rank":16,"last_match":"L 66-88 vs. China (FIBA Asia Cup)","is_end_of_season":1,"is_game_day":1,"is_year_anchor":0,"year_anchor_label":"","tournament_finishes":[],"continental_winner":0},{"date":"2015-09-13","rating":-23.175,"rank":72,"conf_rank":16,"last_match":"L 66-88 vs. China (FIBA Asia Cup)","is_end_of_season":0,"is_game_day":1,"is_year_anchor":0,"year_anchor_label":"","tournament_finishes":[],"continental_winner":0},{"date":"2015-09-15","rating":-22.633,"rank":71,"conf_rank":16,"last_match":"L 66-88 vs. China (FIBA Asia Cup)","is_end_of_season":0,"is_game_day":1,"is_year_anchor":0,"year_anchor_label":"","tournament_finishes":[],"continental_winner":0},{"date":"2015-09-16","rating":-21.041,"rank":69,"conf_rank":14,"last_match":"L 66-88 vs. China (FIBA Asia Cup)","is_end_of_season":0,"is_game_day":1,"is_year_anchor":0,"year_anchor_label":"","tournament_finishes":[],"continental_winner":0},{"date":"2015-09-17","rating":-20.227,"rank":68,"conf_rank":13,"last_match":"L 66-88 vs. China (FIBA Asia Cup)","is_end_of_season":0,"is_game_day":1,"is_year_anchor":0,"year_anchor_label":"","tournament_finishes":[],"continental_winner":0},{"date":"2015-09-18","rating":-20.239,"rank":68,"conf_rank":13,"last_match":"L 66-88 vs. China (FIBA Asia Cup)","is_end_of_season":0,"is_game_day":1,"is_year_anchor":0,"year_anchor_label":"","tournament_finishes":[],"continental_winner":0},{"date":"2015-09-20","rating":-22.372,"rank":68,"conf_rank":13,"last_match":"L 66-88 vs. China (FIBA Asia Cup)","is_end_of_season":1,"is_game_day":1,"is_year_anchor":0,"year_anchor_label":"","tournament_finishes":[],"continental_winner":0},{"date":"2015-09-23","rating":-20.328,"rank":68,"conf_rank":13,"last_match":"L 66-88 vs. China (FIBA Asia Cup)","is_end_of_season":0,"is_game_day":1,"is_year_anchor":0,"year_anchor_label":"","tournament_finishes":[],"continental_winner":0},{"date":"2015-09-24","rating":-19.352,"rank":68,"conf_rank":13,"last_match":"L 66-88 vs. China (FIBA Asia Cup)","is_end_of_season":0,"is_game_day":1,"is_year_anchor":0,"year_anchor_label":"","tournament_finishes":[],"continental_winner":0},{"date":"2015-09-25","rating":-19.988,"rank":67,"conf_rank":12,"last_match":"L 66-88 vs. China (FIBA Asia Cup)","is_end_of_season":0,"is_game_day":1,"is_year_anchor":0,"year_anchor_label":"","tournament_finishes":[],"continental_winner":0},{"date":"2015-09-27","rating":-19.782,"rank":70,"conf_rank":15,"last_match":"L 66-88 vs. China (FIBA Asia Cup)","is_end_of_season":0,"is_game_day":1,"is_year_anchor":0,"year_anchor_label":"","tournament_finishes":[],"continental_winner":0},{"date":"2015-09-28","rating":-19.841,"rank":70,"conf_rank":15,"last_match":"L 66-88 vs. China (FIBA Asia Cup)","is_end_of_season":0,"is_game_day":1,"is_year_anchor":0,"year_anchor_label":"","tournament_finishes":[],"continental_winner":0},{"date":"2015-09-29","rating":-19.818,"rank":69,"conf_rank":14,"last_match":"L 66-88 vs. China (FIBA Asia Cup)","is_end_of_season":0,"is_game_day":1,"is_year_anchor":0,"year_anchor_label":"","tournament_finishes":[],"continental_winner":0},{"date":"2015-10-01","rating":-19.916,"rank":69,"conf_rank":14,"last_match":"L 66-88 vs. China (FIBA Asia Cup)","is_end_of_season":0,"is_game_day":1,"is_year_anchor":0,"year_anchor_label":"","tournament_finishes":[],"continental_winner":0},{"date":"2015-10-02","rating":-19.781,"rank":69,"conf_rank":14,"last_match":"L 66-88 vs. China (FIBA Asia Cup)","is_end_of_season":0,"is_game_day":1,"is_year_anchor":0,"year_anchor_label":"","tournament_finishes":[],"continental_winner":0},{"date":"2015-10-03","rating":-19.712,"rank":69,"conf_rank":14,"last_match":"L 66-88 vs. China (FIBA Asia Cup)","is_end_of_season":1,"is_game_day":1,"is_year_anchor":1,"year_anchor_label":"End of year","tournament_finishes":[],"continental_winner":0}],"2016":[{"date":"2016-08-06","rating":-17.418,"rank":66,"conf_rank":14,"last_match":"L 66-88 vs. China (FIBA Asia Cup)","is_end_of_season":0,"is_game_day":1,"is_year_anchor":0,"year_anchor_label":"","tournament_finishes":[],"continental_winner":0},{"date":"2016-08-07","rating":-17.022,"rank":66,"conf_rank":14,"last_match":"L 66-88 vs. China (FIBA Asia Cup)","is_end_of_season":0,"is_game_day":1,"is_year_anchor":0,"year_anchor_label":"","tournament_finishes":[],"continental_winner":0},{"date":"2016-08-08","rating":-18.023,"rank":66,"conf_rank":14,"last_match":"L 66-88 vs. China (FIBA Asia Cup)","is_end_of_season":0,"is_game_day":1,"is_year_anchor":0,"year_anchor_label":"","tournament_finishes":[],"continental_winner":0},{"date":"2016-08-09","rating":-18.15,"rank":66,"conf_rank":14,"last_match":"L 66-88 vs. China (FIBA Asia Cup)","is_end_of_season":0,"is_game_day":1,"is_year_anchor":0,"year_anchor_label":"","tournament_finishes":[],"continental_winner":0},{"date":"2016-08-10","rating":-18.047,"rank":66,"conf_rank":14,"last_match":"L 66-88 vs. China (FIBA Asia Cup)","is_end_of_season":0,"is_game_day":1,"is_year_anchor":0,"year_anchor_label":"","tournament_finishes":[],"continental_winner":0},{"date":"2016-08-11","rating":-18.185,"rank":66,"conf_rank":14,"last_match":"L 66-88 vs. China (FIBA Asia Cup)","is_end_of_season":0,"is_game_day":1,"is_year_anchor":0,"year_anchor_label":"","tournament_finishes":[],"continental_winner":0},{"date":"2016-08-12","rating":-18.521,"rank":66,"conf_rank":14,"last_match":"L 66-88 vs. China (FIBA Asia Cup)","is_end_of_season":0,"is_game_day":1,"is_year_anchor":0,"year_anchor_label":"","tournament_finishes":[],"continental_winner":0},{"date":"2016-08-13","rating":-18.769,"rank":67,"conf_rank":14,"last_match":"L 66-88 vs. China (FIBA Asia Cup)","is_end_of_season":0,"is_game_day":1,"is_year_anchor":0,"year_anchor_label":"","tournament_finishes":[],"continental_winner":0},{"date":"2016-08-14","rating":-19.119,"rank":68,"conf_rank":14,"last_match":"L 66-88 vs. China (FIBA Asia Cup)","is_end_of_season":0,"is_game_day":1,"is_year_anchor":0,"year_anchor_label":"","tournament_finishes":[],"continental_winner":0},{"date":"2016-08-15","rating":-18.949,"rank":67,"conf_rank":14,"last_match":"L 66-88 vs. China (FIBA Asia Cup)","is_end_of_season":0,"is_game_day":1,"is_year_anchor":0,"year_anchor_label":"","tournament_finishes":[],"continental_winner":0},{"date":"2016-08-17","rating":-18.854,"rank":67,"conf_rank":14,"last_match":"L 66-88 vs. China (FIBA Asia Cup)","is_end_of_season":0,"is_game_day":1,"is_year_anchor":0,"year_anchor_label":"","tournament_finishes":[],"continental_winner":0},{"date":"2016-08-19","rating":-19.002,"rank":67,"conf_rank":14,"last_match":"L 66-88 vs. China (FIBA Asia Cup)","is_end_of_season":0,"is_game_day":1,"is_year_anchor":0,"year_anchor_label":"","tournament_finishes":[],"continental_winner":0},{"date":"2016-08-21","rating":-18.99,"rank":67,"conf_rank":14,"last_match":"L 66-88 vs. China (FIBA Asia Cup)","is_end_of_season":1,"is_game_day":1,"is_year_anchor":1,"year_anchor_label":"End of year","tournament_finishes":[],"continental_winner":0}],"2017":[{"date":"2017-08-02","rating":-20.109,"rank":68,"conf_rank":14,"last_match":"L 66-88 vs. China (FIBA Asia Cup)","is_end_of_season":0,"is_game_day":1,"is_year_anchor":0,"year_anchor_label":"","tournament_finishes":[],"continental_winner":0},{"date":"2017-08-05","rating":-17.74,"rank":null,"conf_rank":null,"last_match":"L 66-88 vs. China (FIBA Asia Cup)","is_end_of_season":0,"is_game_day":1,"is_year_anchor":1,"year_anchor_label":"End of year","tournament_finishes":[],"continental_winner":0}],"2021":[{"date":"2021-11-26","rating":-8.274,"rank":null,"conf_rank":null,"last_match":"L 66-82 vs. Iran (WC Qualifiers)","is_end_of_season":0,"is_game_day":1,"is_year_anchor":0,"year_anchor_label":"","tournament_finishes":[],"continental_winner":0},{"date":"2021-11-27","rating":-8.547,"rank":null,"conf_rank":null,"last_match":"L 66-82 vs. Iran (WC Qualifiers)","is_end_of_season":0,"is_game_day":1,"is_year_anchor":0,"year_anchor_label":"","tournament_finishes":[],"continental_winner":0},{"date":"2021-11-28","rating":-9.494,"rank":null,"conf_rank":null,"last_match":"L 66-82 vs. Iran (WC Qualifiers)","is_end_of_season":0,"is_game_day":1,"is_year_anchor":0,"year_anchor_label":"","tournament_finishes":[],"continental_winner":0},{"date":"2021-11-29","rating":-14.844,"rank":null,"conf_rank":null,"last_match":"L 64-100 vs. Iran (WC Qualifiers)","is_end_of_season":0,"is_game_day":1,"is_year_anchor":1,"year_anchor_label":"End of year","tournament_finishes":[],"continental_winner":0}],"2022":[{"date":"2022-02-24","rating":-21.826,"rank":null,"conf_rank":null,"last_match":"L 64-80 vs. Syria (WC Qualifiers)","is_end_of_season":0,"is_game_day":1,"is_year_anchor":0,"year_anchor_label":"","tournament_finishes":[],"continental_winner":0},{"date":"2022-02-25","rating":-22.109,"rank":null,"conf_rank":null,"last_match":"L 64-80 vs. Syria (WC Qualifiers)","is_end_of_season":0,"is_game_day":1,"is_year_anchor":0,"year_anchor_label":"","tournament_finishes":[],"continental_winner":0},{"date":"2022-02-26","rating":-21.959,"rank":null,"conf_rank":null,"last_match":"L 64-80 vs. Syria (WC Qualifiers)","is_end_of_season":0,"is_game_day":1,"is_year_anchor":0,"year_anchor_label":"","tournament_finishes":[],"continental_winner":0},{"date":"2022-02-27","rating":-23.118,"rank":82,"conf_rank":16,"last_match":"L 48-95 vs. Kazakhstan (WC Qualifiers)","is_end_of_season":0,"is_game_day":1,"is_year_anchor":0,"year_anchor_label":"","tournament_finishes":[],"continental_winner":0},{"date":"2022-02-28","rating":-23.128,"rank":83,"conf_rank":16,"last_match":"L 48-95 vs. Kazakhstan (WC Qualifiers)","is_end_of_season":0,"is_game_day":1,"is_year_anchor":0,"year_anchor_label":"","tournament_finishes":[],"continental_winner":0},{"date":"2022-06-30","rating":-22.279,"rank":83,"conf_rank":16,"last_match":"L 48-95 vs. Kazakhstan (WC Qualifiers)","is_end_of_season":0,"is_game_day":1,"is_year_anchor":0,"year_anchor_label":"","tournament_finishes":[],"continental_winner":0},{"date":"2022-07-01","rating":-17.896,"rank":78,"conf_rank":14,"last_match":"W 76-67 vs. Syria (WC Qualifiers)","is_end_of_season":0,"is_game_day":1,"is_year_anchor":0,"year_anchor_label":"","tournament_finishes":[],"continental_winner":0},{"date":"2022-07-02","rating":-18.212,"rank":76,"conf_rank":14,"last_match":"W 76-67 vs. Syria (WC Qualifiers)","is_end_of_season":0,"is_game_day":1,"is_year_anchor":0,"year_anchor_label":"","tournament_finishes":[],"continental_winner":0},{"date":"2022-07-03","rating":-18.27,"rank":77,"conf_rank":14,"last_match":"W 76-67 vs. Syria (WC Qualifiers)","is_end_of_season":0,"is_game_day":1,"is_year_anchor":0,"year_anchor_label":"","tournament_finishes":[],"continental_winner":0},{"date":"2022-07-04","rating":-13.763,"rank":72,"conf_rank":14,"last_match":"W 62-51 vs. Kazakhstan (WC Qualifiers)","is_end_of_season":0,"is_game_day":1,"is_year_anchor":0,"year_anchor_label":"","tournament_finishes":[],"continental_winner":0},{"date":"2022-07-07","rating":-13.786,"rank":72,"conf_rank":14,"last_match":"W 62-51 vs. Kazakhstan (WC Qualifiers)","is_end_of_season":0,"is_game_day":1,"is_year_anchor":0,"year_anchor_label":"","tournament_finishes":[],"continental_winner":0},{"date":"2022-07-12","rating":-18.52,"rank":78,"conf_rank":14,"last_match":"L 84-102 vs. Chinese Taipei (FIBA Asia Cup)","is_end_of_season":0,"is_game_day":1,"is_year_anchor":0,"year_anchor_label":"","tournament_finishes":[],"continental_winner":0},{"date":"2022-07-13","rating":-20.557,"rank":82,"conf_rank":17,"last_match":"L 84-102 vs. Chinese Taipei (FIBA Asia Cup)","is_end_of_season":0,"is_game_day":1,"is_year_anchor":0,"year_anchor_label":"","tournament_finishes":[],"continental_winner":0},{"date":"2022-07-14","rating":-15.387,"rank":76,"conf_rank":15,"last_match":"L 79-80 vs. China (FIBA Asia Cup)","is_end_of_season":0,"is_game_day":1,"is_year_anchor":0,"year_anchor_label":"","tournament_finishes":[],"continental_winner":0},{"date":"2022-07-15","rating":-16.536,"rank":75,"conf_rank":14,"last_match":"L 79-80 vs. China (FIBA Asia Cup)","is_end_of_season":0,"is_game_day":1,"is_year_anchor":0,"year_anchor_label":"","tournament_finishes":[],"continental_winner":0},{"date":"2022-07-16","rating":-14.336,"rank":73,"conf_rank":14,"last_match":"L 73-78 vs. South Korea (FIBA Asia Cup)","is_end_of_season":0,"is_game_day":1,"is_year_anchor":0,"year_anchor_label":"","tournament_finishes":[],"continental_winner":0},{"date":"2022-07-17","rating":-14.102,"rank":73,"conf_rank":14,"last_match":"L 73-78 vs. South Korea (FIBA Asia Cup)","is_end_of_season":0,"is_game_day":1,"is_year_anchor":0,"year_anchor_label":"","tournament_finishes":[],"continental_winner":0},{"date":"2022-07-18","rating":-13.407,"rank":71,"conf_rank":13,"last_match":"L 73-78 vs. South Korea (FIBA Asia Cup)","is_end_of_season":0,"is_game_day":1,"is_year_anchor":0,"year_anchor_label":"","tournament_finishes":[],"continental_winner":0},{"date":"2022-07-19","rating":-13.362,"rank":71,"conf_rank":13,"last_match":"L 73-78 vs. South Korea (FIBA Asia Cup)","is_end_of_season":0,"is_game_day":1,"is_year_anchor":0,"year_anchor_label":"","tournament_finishes":[],"continental_winner":0},{"date":"2022-07-20","rating":-13.888,"rank":72,"conf_rank":14,"last_match":"L 73-78 vs. South Korea (FIBA Asia Cup)","is_end_of_season":0,"is_game_day":1,"is_year_anchor":0,"year_anchor_label":"","tournament_finishes":[],"continental_winner":0},{"date":"2022-07-21","rating":-13.945,"rank":72,"conf_rank":14,"last_match":"L 73-78 vs. South Korea (FIBA Asia Cup)","is_end_of_season":0,"is_game_day":1,"is_year_anchor":0,"year_anchor_label":"","tournament_finishes":[],"continental_winner":0},{"date":"2022-07-23","rating":-13.944,"rank":73,"conf_rank":14,"last_match":"L 73-78 vs. South Korea (FIBA Asia Cup)","is_end_of_season":0,"is_game_day":1,"is_year_anchor":0,"year_anchor_label":"","tournament_finishes":[],"continental_winner":0},{"date":"2022-07-24","rating":-13.876,"rank":72,"conf_rank":14,"last_match":"L 73-78 vs. South Korea (FIBA Asia Cup)","is_end_of_season":1,"is_game_day":1,"is_year_anchor":1,"year_anchor_label":"End of FIBA Asia Cup","tournament_finishes":[],"continental_winner":0},{"date":"2022-08-24","rating":-13.707,"rank":72,"conf_rank":14,"last_match":"L 73-78 vs. South Korea (FIBA Asia Cup)","is_end_of_season":0,"is_game_day":1,"is_year_anchor":0,"year_anchor_label":"","tournament_finishes":[],"continental_winner":0},{"date":"2022-08-25","rating":-12.967,"rank":71,"conf_rank":13,"last_match":"L 50-104 vs. Australia (WC Qualifiers)","is_end_of_season":0,"is_game_day":1,"is_year_anchor":0,"year_anchor_label":"","tournament_finishes":[],"continental_winner":0},{"date":"2022-08-26","rating":-13.009,"rank":71,"conf_rank":13,"last_match":"L 50-104 vs. Australia (WC Qualifiers)","is_end_of_season":0,"is_game_day":1,"is_year_anchor":0,"year_anchor_label":"","tournament_finishes":[],"continental_winner":0},{"date":"2022-08-27","rating":-13.066,"rank":71,"conf_rank":13,"last_match":"L 50-104 vs. Australia (WC Qualifiers)","is_end_of_season":0,"is_game_day":1,"is_year_anchor":0,"year_anchor_label":"","tournament_finishes":[],"continental_winner":0},{"date":"2022-08-28","rating":-13.003,"rank":72,"conf_rank":13,"last_match":"L 50-104 vs. Australia (WC Qualifiers)","is_end_of_season":0,"is_game_day":1,"is_year_anchor":0,"year_anchor_label":"","tournament_finishes":[],"continental_winner":0},{"date":"2022-08-29","rating":-12.625,"rank":71,"conf_rank":13,"last_match":"L 67-80 vs. China (WC Qualifiers)","is_end_of_season":0,"is_game_day":1,"is_year_anchor":0,"year_anchor_label":"","tournament_finishes":[],"continental_winner":0},{"date":"2022-08-30","rating":-12.89,"rank":71,"conf_rank":13,"last_match":"L 67-80 vs. China (WC Qualifiers)","is_end_of_season":0,"is_game_day":1,"is_year_anchor":0,"year_anchor_label":"","tournament_finishes":[],"continental_winner":0},{"date":"2022-09-01","rating":-12.896,"rank":72,"conf_rank":13,"last_match":"L 67-80 vs. China (WC Qualifiers)","is_end_of_season":0,"is_game_day":1,"is_year_anchor":0,"year_anchor_label":"","tournament_finishes":[],"continental_winner":0},{"date":"2022-09-02","rating":-13.079,"rank":72,"conf_rank":13,"last_match":"L 67-80 vs. China (WC Qualifiers)","is_end_of_season":0,"is_game_day":1,"is_year_anchor":0,"year_anchor_label":"","tournament_finishes":[],"continental_winner":0},{"date":"2022-09-03","rating":-12.937,"rank":71,"conf_rank":13,"last_match":"L 67-80 vs. China (WC Qualifiers)","is_end_of_season":0,"is_game_day":1,"is_year_anchor":0,"year_anchor_label":"","tournament_finishes":[],"continental_winner":0},{"date":"2022-09-04","rating":-13.098,"rank":72,"conf_rank":13,"last_match":"L 67-80 vs. China (WC Qualifiers)","is_end_of_season":0,"is_game_day":1,"is_year_anchor":0,"year_anchor_label":"","tournament_finishes":[],"continental_winner":0},{"date":"2022-09-05","rating":-13.1,"rank":71,"conf_rank":13,"last_match":"L 67-80 vs. China (WC Qualifiers)","is_end_of_season":0,"is_game_day":1,"is_year_anchor":0,"year_anchor_label":"","tournament_finishes":[],"continental_winner":0},{"date":"2022-09-06","rating":-12.883,"rank":72,"conf_rank":13,"last_match":"L 67-80 vs. China (WC Qualifiers)","is_end_of_season":0,"is_game_day":1,"is_year_anchor":0,"year_anchor_label":"","tournament_finishes":[],"continental_winner":0},{"date":"2022-09-07","rating":-12.867,"rank":72,"conf_rank":13,"last_match":"L 67-80 vs. China (WC Qualifiers)","is_end_of_season":0,"is_game_day":1,"is_year_anchor":0,"year_anchor_label":"","tournament_finishes":[],"continental_winner":0},{"date":"2022-09-08","rating":-12.794,"rank":72,"conf_rank":13,"last_match":"L 67-80 vs. China (WC Qualifiers)","is_end_of_season":0,"is_game_day":1,"is_year_anchor":0,"year_anchor_label":"","tournament_finishes":[],"continental_winner":0},{"date":"2022-09-10","rating":-12.749,"rank":72,"conf_rank":13,"last_match":"L 67-80 vs. China (WC Qualifiers)","is_end_of_season":0,"is_game_day":1,"is_year_anchor":0,"year_anchor_label":"","tournament_finishes":[],"continental_winner":0},{"date":"2022-09-11","rating":-12.671,"rank":72,"conf_rank":13,"last_match":"L 67-80 vs. China (WC Qualifiers)","is_end_of_season":1,"is_game_day":1,"is_year_anchor":0,"year_anchor_label":"","tournament_finishes":[],"continental_winner":0},{"date":"2022-09-13","rating":-12.636,"rank":72,"conf_rank":13,"last_match":"L 67-80 vs. China (WC Qualifiers)","is_end_of_season":0,"is_game_day":1,"is_year_anchor":0,"year_anchor_label":"","tournament_finishes":[],"continental_winner":0},{"date":"2022-09-14","rating":-12.608,"rank":72,"conf_rank":13,"last_match":"L 67-80 vs. China (WC Qualifiers)","is_end_of_season":0,"is_game_day":1,"is_year_anchor":0,"year_anchor_label":"","tournament_finishes":[],"continental_winner":0},{"date":"2022-09-16","rating":-12.59,"rank":72,"conf_rank":13,"last_match":"L 67-80 vs. China (WC Qualifiers)","is_end_of_season":0,"is_game_day":1,"is_year_anchor":0,"year_anchor_label":"","tournament_finishes":[],"continental_winner":0},{"date":"2022-09-18","rating":-12.603,"rank":72,"conf_rank":13,"last_match":"L 67-80 vs. China (WC Qualifiers)","is_end_of_season":1,"is_game_day":1,"is_year_anchor":0,"year_anchor_label":"","tournament_finishes":[],"continental_winner":0},{"date":"2022-11-10","rating":-12.615,"rank":72,"conf_rank":13,"last_match":"L 67-80 vs. China (WC Qualifiers)","is_end_of_season":0,"is_game_day":1,"is_year_anchor":0,"year_anchor_label":"","tournament_finishes":[],"continental_winner":0},{"date":"2022-11-11","rating":-12.568,"rank":72,"conf_rank":13,"last_match":"L 74-87 vs. Japan (WC Qualifiers)","is_end_of_season":0,"is_game_day":1,"is_year_anchor":0,"year_anchor_label":"","tournament_finishes":[],"continental_winner":0},{"date":"2022-11-13","rating":-12.67,"rank":72,"conf_rank":13,"last_match":"L 74-87 vs. Japan (WC Qualifiers)","is_end_of_season":0,"is_game_day":1,"is_year_anchor":0,"year_anchor_label":"","tournament_finishes":[],"continental_winner":0},{"date":"2022-11-14","rating":-12.671,"rank":72,"conf_rank":13,"last_match":"L 67-80 vs. China (WC Qualifiers)","is_end_of_season":0,"is_game_day":1,"is_year_anchor":0,"year_anchor_label":"","tournament_finishes":[],"continental_winner":0}],"2023":[{"date":"2023-02-23","rating":-12.539,"rank":71,"conf_rank":12,"last_match":"L 51-83 vs. Australia (WC Qualifiers)","is_end_of_season":0,"is_game_day":1,"is_year_anchor":0,"year_anchor_label":"","tournament_finishes":[],"continental_winner":0},{"date":"2023-02-24","rating":-12.974,"rank":72,"conf_rank":13,"last_match":"L 51-83 vs. Australia (WC Qualifiers)","is_end_of_season":0,"is_game_day":1,"is_year_anchor":0,"year_anchor_label":"","tournament_finishes":[],"continental_winner":0},{"date":"2023-02-25","rating":-12.998,"rank":72,"conf_rank":13,"last_match":"L 51-83 vs. Australia (WC Qualifiers)","is_end_of_season":0,"is_game_day":1,"is_year_anchor":0,"year_anchor_label":"","tournament_finishes":[],"continental_winner":0},{"date":"2023-02-26","rating":-13.453,"rank":73,"conf_rank":13,"last_match":"L 72-95 vs. Japan (WC Qualifiers)","is_end_of_season":0,"is_game_day":1,"is_year_anchor":0,"year_anchor_label":"","tournament_finishes":[],"continental_winner":0},{"date":"2023-02-27","rating":-13.492,"rank":73,"conf_rank":13,"last_match":"L 72-95 vs. Japan (WC Qualifiers)","is_end_of_season":0,"is_game_day":1,"is_year_anchor":0,"year_anchor_label":"","tournament_finishes":[],"continental_winner":0},{"date":"2023-08-01","rating":-13.21,"rank":72,"conf_rank":13,"last_match":"L 72-95 vs. Japan (WC Qualifiers)","is_end_of_season":0,"is_game_day":1,"is_year_anchor":0,"year_anchor_label":"","tournament_finishes":[],"continental_winner":0},{"date":"2023-08-25","rating":-12.538,"rank":71,"conf_rank":13,"last_match":"L 72-95 vs. Japan (WC Qualifiers)","is_end_of_season":0,"is_game_day":1,"is_year_anchor":0,"year_anchor_label":"","tournament_finishes":[],"continental_winner":0},{"date":"2023-08-26","rating":-13.965,"rank":71,"conf_rank":13,"last_match":"L 72-95 vs. Japan (WC Qualifiers)","is_end_of_season":0,"is_game_day":1,"is_year_anchor":0,"year_anchor_label":"","tournament_finishes":[],"continental_winner":0},{"date":"2023-08-27","rating":-13.538,"rank":70,"conf_rank":12,"last_match":"L 72-95 vs. Japan (WC Qualifiers)","is_end_of_season":0,"is_game_day":1,"is_year_anchor":0,"year_anchor_label":"","tournament_finishes":[],"continental_winner":0},{"date":"2023-08-28","rating":-14.582,"rank":72,"conf_rank":12,"last_match":"L 72-95 vs. Japan (WC Qualifiers)","is_end_of_season":0,"is_game_day":1,"is_year_anchor":0,"year_anchor_label":"","tournament_finishes":[],"continental_winner":0},{"date":"2023-08-29","rating":-14.488,"rank":73,"conf_rank":13,"last_match":"L 72-95 vs. Japan (WC Qualifiers)","is_end_of_season":0,"is_game_day":1,"is_year_anchor":0,"year_anchor_label":"","tournament_finishes":[],"continental_winner":0},{"date":"2023-08-30","rating":-14.884,"rank":73,"conf_rank":13,"last_match":"L 72-95 vs. Japan (WC Qualifiers)","is_end_of_season":0,"is_game_day":1,"is_year_anchor":0,"year_anchor_label":"","tournament_finishes":[],"continental_winner":0},{"date":"2023-08-31","rating":-14.403,"rank":72,"conf_rank":12,"last_match":"L 72-95 vs. Japan (WC Qualifiers)","is_end_of_season":0,"is_game_day":1,"is_year_anchor":0,"year_anchor_label":"","tournament_finishes":[],"continental_winner":0},{"date":"2023-09-01","rating":-14.644,"rank":72,"conf_rank":12,"last_match":"L 72-95 vs. Japan (WC Qualifiers)","is_end_of_season":0,"is_game_day":1,"is_year_anchor":0,"year_anchor_label":"","tournament_finishes":[],"continental_winner":0},{"date":"2023-09-02","rating":-15.325,"rank":72,"conf_rank":13,"last_match":"L 72-95 vs. Japan (WC Qualifiers)","is_end_of_season":0,"is_game_day":1,"is_year_anchor":0,"year_anchor_label":"","tournament_finishes":[],"continental_winner":0},{"date":"2023-09-03","rating":-15.094,"rank":72,"conf_rank":13,"last_match":"L 72-95 vs. Japan (WC Qualifiers)","is_end_of_season":0,"is_game_day":1,"is_year_anchor":0,"year_anchor_label":"","tournament_finishes":[],"continental_winner":0},{"date":"2023-09-05","rating":-14.846,"rank":72,"conf_rank":13,"last_match":"L 72-95 vs. Japan (WC Qualifiers)","is_end_of_season":0,"is_game_day":1,"is_year_anchor":0,"year_anchor_label":"","tournament_finishes":[],"continental_winner":0},{"date":"2023-09-06","rating":-14.918,"rank":72,"conf_rank":13,"last_match":"L 72-95 vs. Japan (WC Qualifiers)","is_end_of_season":0,"is_game_day":1,"is_year_anchor":0,"year_anchor_label":"","tournament_finishes":[],"continental_winner":0},{"date":"2023-09-07","rating":-14.872,"rank":72,"conf_rank":13,"last_match":"L 72-95 vs. Japan (WC Qualifiers)","is_end_of_season":0,"is_game_day":1,"is_year_anchor":0,"year_anchor_label":"","tournament_finishes":[],"continental_winner":0},{"date":"2023-09-08","rating":-14.808,"rank":72,"conf_rank":13,"last_match":"L 72-95 vs. Japan (WC Qualifiers)","is_end_of_season":0,"is_game_day":1,"is_year_anchor":0,"year_anchor_label":"","tournament_finishes":[],"continental_winner":0},{"date":"2023-09-09","rating":-14.837,"rank":72,"conf_rank":13,"last_match":"L 72-95 vs. Japan (WC Qualifiers)","is_end_of_season":0,"is_game_day":1,"is_year_anchor":0,"year_anchor_label":"","tournament_finishes":[],"continental_winner":0},{"date":"2023-09-10","rating":-14.827,"rank":72,"conf_rank":13,"last_match":"L 72-95 vs. Japan (WC Qualifiers)","is_end_of_season":1,"is_game_day":1,"is_year_anchor":1,"year_anchor_label":"End of year","tournament_finishes":[],"continental_winner":0}],"2024":[{"date":"2024-07-27","rating":-14.048,"rank":71,"conf_rank":13,"last_match":"L 72-95 vs. Japan (WC Qualifiers)","is_end_of_season":0,"is_game_day":1,"is_year_anchor":0,"year_anchor_label":"","tournament_finishes":[],"continental_winner":0},{"date":"2024-07-28","rating":-14.093,"rank":71,"conf_rank":13,"last_match":"L 72-95 vs. Japan (WC Qualifiers)","is_end_of_season":0,"is_game_day":1,"is_year_anchor":0,"year_anchor_label":"","tournament_finishes":[],"continental_winner":0},{"date":"2024-07-30","rating":-13.918,"rank":71,"conf_rank":13,"last_match":"L 72-95 vs. Japan (WC Qualifiers)","is_end_of_season":0,"is_game_day":1,"is_year_anchor":0,"year_anchor_label":"","tournament_finishes":[],"continental_winner":0},{"date":"2024-07-31","rating":-13.911,"rank":71,"conf_rank":13,"last_match":"L 72-95 vs. Japan (WC Qualifiers)","is_end_of_season":0,"is_game_day":1,"is_year_anchor":0,"year_anchor_label":"","tournament_finishes":[],"continental_winner":0},{"date":"2024-08-02","rating":-14.448,"rank":71,"conf_rank":13,"last_match":"L 72-95 vs. Japan (WC Qualifiers)","is_end_of_season":0,"is_game_day":1,"is_year_anchor":0,"year_anchor_label":"","tournament_finishes":[],"continental_winner":0},{"date":"2024-08-03","rating":-14.45,"rank":71,"conf_rank":13,"last_match":"L 72-95 vs. Japan (WC Qualifiers)","is_end_of_season":0,"is_game_day":1,"is_year_anchor":0,"year_anchor_label":"","tournament_finishes":[],"continental_winner":0},{"date":"2024-08-06","rating":-14.447,"rank":71,"conf_rank":13,"last_match":"L 72-95 vs. Japan (WC Qualifiers)","is_end_of_season":0,"is_game_day":1,"is_year_anchor":0,"year_anchor_label":"","tournament_finishes":[],"continental_winner":0},{"date":"2024-08-08","rating":-14.453,"rank":71,"conf_rank":13,"last_match":"L 72-95 vs. Japan (WC Qualifiers)","is_end_of_season":0,"is_game_day":1,"is_year_anchor":0,"year_anchor_label":"","tournament_finishes":[],"continental_winner":0},{"date":"2024-08-10","rating":-14.484,"rank":71,"conf_rank":13,"last_match":"L 72-95 vs. Japan (WC Qualifiers)","is_end_of_season":1,"is_game_day":1,"is_year_anchor":1,"year_anchor_label":"End of year","tournament_finishes":[],"continental_winner":0}],"2025":[{"date":"2025-08-05","rating":-15.545,"rank":70,"conf_rank":12,"last_match":"L 72-95 vs. Japan (WC Qualifiers)","is_end_of_season":0,"is_game_day":1,"is_year_anchor":0,"year_anchor_label":"","tournament_finishes":[],"continental_winner":0},{"date":"2025-08-06","rating":-15.632,"rank":71,"conf_rank":13,"last_match":"L 72-95 vs. Japan (WC Qualifiers)","is_end_of_season":0,"is_game_day":1,"is_year_anchor":0,"year_anchor_label":"","tournament_finishes":[],"continental_winner":0},{"date":"2025-08-07","rating":-15.1,"rank":70,"conf_rank":12,"last_match":"L 72-95 vs. Japan (WC Qualifiers)","is_end_of_season":0,"is_game_day":1,"is_year_anchor":0,"year_anchor_label":"","tournament_finishes":[],"continental_winner":0},{"date":"2025-08-08","rating":-15.061,"rank":70,"conf_rank":12,"last_match":"L 72-95 vs. Japan (WC Qualifiers)","is_end_of_season":0,"is_game_day":1,"is_year_anchor":0,"year_anchor_label":"","tournament_finishes":[],"continental_winner":0},{"date":"2025-08-09","rating":-14.955,"rank":70,"conf_rank":12,"last_match":"L 72-95 vs. Japan (WC Qualifiers)","is_end_of_season":0,"is_game_day":1,"is_year_anchor":0,"year_anchor_label":"","tournament_finishes":[],"continental_winner":0},{"date":"2025-08-10","rating":-14.687,"rank":69,"conf_rank":12,"last_match":"L 72-95 vs. Japan (WC Qualifiers)","is_end_of_season":0,"is_game_day":1,"is_year_anchor":0,"year_anchor_label":"","tournament_finishes":[],"continental_winner":0},{"date":"2025-08-11","rating":-14.477,"rank":69,"conf_rank":12,"last_match":"L 72-95 vs. Japan (WC Qualifiers)","is_end_of_season":0,"is_game_day":1,"is_year_anchor":0,"year_anchor_label":"","tournament_finishes":[],"continental_winner":0},{"date":"2025-08-12","rating":-14.868,"rank":71,"conf_rank":12,"last_match":"L 72-95 vs. Japan (WC Qualifiers)","is_end_of_season":0,"is_game_day":1,"is_year_anchor":0,"year_anchor_label":"","tournament_finishes":[],"continental_winner":0},{"date":"2025-08-13","rating":-14.522,"rank":71,"conf_rank":12,"last_match":"L 72-95 vs. Japan (WC Qualifiers)","is_end_of_season":0,"is_game_day":1,"is_year_anchor":0,"year_anchor_label":"","tournament_finishes":[],"continental_winner":0},{"date":"2025-08-14","rating":-14.489,"rank":71,"conf_rank":12,"last_match":"L 72-95 vs. Japan (WC Qualifiers)","is_end_of_season":0,"is_game_day":1,"is_year_anchor":0,"year_anchor_label":"","tournament_finishes":[],"continental_winner":0},{"date":"2025-08-15","rating":-14.621,"rank":71,"conf_rank":12,"last_match":"L 72-95 vs. Japan (WC Qualifiers)","is_end_of_season":0,"is_game_day":1,"is_year_anchor":0,"year_anchor_label":"","tournament_finishes":[],"continental_winner":0},{"date":"2025-08-16","rating":-14.302,"rank":71,"conf_rank":12,"last_match":"L 72-95 vs. Japan (WC Qualifiers)","is_end_of_season":0,"is_game_day":1,"is_year_anchor":0,"year_anchor_label":"","tournament_finishes":[],"continental_winner":0},{"date":"2025-08-17","rating":-13.867,"rank":71,"conf_rank":12,"last_match":"L 72-95 vs. Japan (WC Qualifiers)","is_end_of_season":1,"is_game_day":1,"is_year_anchor":0,"year_anchor_label":"","tournament_finishes":[],"continental_winner":0},{"date":"2025-08-18","rating":-14.02,"rank":71,"conf_rank":12,"last_match":"L 72-95 vs. Japan (WC Qualifiers)","is_end_of_season":0,"is_game_day":1,"is_year_anchor":0,"year_anchor_label":"","tournament_finishes":[],"continental_winner":0},{"date":"2025-08-19","rating":-13.862,"rank":71,"conf_rank":12,"last_match":"L 72-95 vs. Japan (WC Qualifiers)","is_end_of_season":0,"is_game_day":1,"is_year_anchor":0,"year_anchor_label":"","tournament_finishes":[],"continental_winner":0},{"date":"2025-08-20","rating":-13.925,"rank":71,"conf_rank":12,"last_match":"L 72-95 vs. Japan (WC Qualifiers)","is_end_of_season":0,"is_game_day":1,"is_year_anchor":0,"year_anchor_label":"","tournament_finishes":[],"continental_winner":0},{"date":"2025-08-21","rating":-14.104,"rank":71,"conf_rank":12,"last_match":"L 72-95 vs. Japan (WC Qualifiers)","is_end_of_season":0,"is_game_day":1,"is_year_anchor":0,"year_anchor_label":"","tournament_finishes":[],"continental_winner":0},{"date":"2025-08-22","rating":-13.81,"rank":71,"conf_rank":12,"last_match":"L 72-95 vs. Japan (WC Qualifiers)","is_end_of_season":0,"is_game_day":1,"is_year_anchor":0,"year_anchor_label":"","tournament_finishes":[],"continental_winner":0},{"date":"2025-08-23","rating":-14.066,"rank":71,"conf_rank":12,"last_match":"L 72-95 vs. Japan (WC Qualifiers)","is_end_of_season":0,"is_game_day":1,"is_year_anchor":0,"year_anchor_label":"","tournament_finishes":[],"continental_winner":0},{"date":"2025-08-24","rating":-14.007,"rank":71,"conf_rank":12,"last_match":"L 72-95 vs. Japan (WC Qualifiers)","is_end_of_season":1,"is_game_day":1,"is_year_anchor":0,"year_anchor_label":"","tournament_finishes":[],"continental_winner":0},{"date":"2025-08-25","rating":-14.122,"rank":71,"conf_rank":12,"last_match":"L 72-95 vs. Japan (WC Qualifiers)","is_end_of_season":0,"is_game_day":1,"is_year_anchor":0,"year_anchor_label":"","tournament_finishes":[],"continental_winner":0},{"date":"2025-08-26","rating":-14.087,"rank":71,"conf_rank":12,"last_match":"L 72-95 vs. Japan (WC Qualifiers)","is_end_of_season":0,"is_game_day":1,"is_year_anchor":0,"year_anchor_label":"","tournament_finishes":[],"continental_winner":0},{"date":"2025-08-27","rating":-14.113,"rank":71,"conf_rank":12,"last_match":"L 72-95 vs. Japan (WC Qualifiers)","is_end_of_season":0,"is_game_day":1,"is_year_anchor":0,"year_anchor_label":"","tournament_finishes":[],"continental_winner":0},{"date":"2025-08-28","rating":-13.827,"rank":71,"conf_rank":12,"last_match":"L 72-95 vs. Japan (WC Qualifiers)","is_end_of_season":0,"is_game_day":1,"is_year_anchor":0,"year_anchor_label":"","tournament_finishes":[],"continental_winner":0},{"date":"2025-08-29","rating":-13.779,"rank":71,"conf_rank":12,"last_match":"L 72-95 vs. Japan (WC Qualifiers)","is_end_of_season":0,"is_game_day":1,"is_year_anchor":0,"year_anchor_label":"","tournament_finishes":[],"continental_winner":0},{"date":"2025-08-30","rating":-13.609,"rank":71,"conf_rank":12,"last_match":"L 72-95 vs. Japan (WC Qualifiers)","is_end_of_season":0,"is_game_day":1,"is_year_anchor":0,"year_anchor_label":"","tournament_finishes":[],"continental_winner":0},{"date":"2025-08-31","rating":-13.609,"rank":71,"conf_rank":12,"last_match":"L 72-95 vs. Japan (WC Qualifiers)","is_end_of_season":1,"is_game_day":1,"is_year_anchor":0,"year_anchor_label":"","tournament_finishes":[],"continental_winner":0},{"date":"2025-09-01","rating":-13.652,"rank":71,"conf_rank":12,"last_match":"L 72-95 vs. Japan (WC Qualifiers)","is_end_of_season":0,"is_game_day":1,"is_year_anchor":0,"year_anchor_label":"","tournament_finishes":[],"continental_winner":0},{"date":"2025-09-02","rating":-13.679,"rank":71,"conf_rank":12,"last_match":"L 72-95 vs. Japan (WC Qualifiers)","is_end_of_season":0,"is_game_day":1,"is_year_anchor":0,"year_anchor_label":"","tournament_finishes":[],"continental_winner":0},{"date":"2025-09-03","rating":-13.689,"rank":71,"conf_rank":12,"last_match":"L 72-95 vs. Japan (WC Qualifiers)","is_end_of_season":0,"is_game_day":1,"is_year_anchor":0,"year_anchor_label":"","tournament_finishes":[],"continental_winner":0},{"date":"2025-09-04","rating":-13.635,"rank":71,"conf_rank":12,"last_match":"L 72-95 vs. Japan (WC Qualifiers)","is_end_of_season":0,"is_game_day":1,"is_year_anchor":0,"year_anchor_label":"","tournament_finishes":[],"continental_winner":0},{"date":"2025-09-06","rating":-13.597,"rank":71,"conf_rank":12,"last_match":"L 72-95 vs. Japan (WC Qualifiers)","is_end_of_season":0,"is_game_day":1,"is_year_anchor":0,"year_anchor_label":"","tournament_finishes":[],"continental_winner":0},{"date":"2025-09-07","rating":-13.654,"rank":71,"conf_rank":12,"last_match":"L 72-95 vs. Japan (WC Qualifiers)","is_end_of_season":0,"is_game_day":1,"is_year_anchor":0,"year_anchor_label":"","tournament_finishes":[],"continental_winner":0},{"date":"2025-09-09","rating":-13.621,"rank":71,"conf_rank":12,"last_match":"L 72-95 vs. Japan (WC Qualifiers)","is_end_of_season":0,"is_game_day":1,"is_year_anchor":0,"year_anchor_label":"","tournament_finishes":[],"continental_winner":0},{"date":"2025-09-10","rating":-13.626,"rank":71,"conf_rank":12,"last_match":"L 72-95 vs. Japan (WC Qualifiers)","is_end_of_season":0,"is_game_day":1,"is_year_anchor":0,"year_anchor_label":"","tournament_finishes":[],"continental_winner":0},{"date":"2025-09-12","rating":-13.709,"rank":71,"conf_rank":12,"last_match":"L 72-95 vs. Japan (WC Qualifiers)","is_end_of_season":0,"is_game_day":1,"is_year_anchor":0,"year_anchor_label":"","tournament_finishes":[],"continental_winner":0},{"date":"2025-09-14","rating":-13.712,"rank":71,"conf_rank":12,"last_match":"L 72-95 vs. Japan (WC Qualifiers)","is_end_of_season":1,"is_game_day":1,"is_year_anchor":1,"year_anchor_label":"End of year","tournament_finishes":[],"continental_winner":0}]}}