{"team":"Colombia","flag":"🇨🇴","confederation":"Americas","seasons":{"1982":[{"date":"1982-08-19","rating":-10.154,"rank":null,"conf_rank":null,"last_match":"L 84-137 vs. Spain (FIBA World Cup)","is_end_of_season":0,"is_game_day":1,"is_year_anchor":0,"year_anchor_label":"","tournament_finishes":[],"continental_winner":0},{"date":"1982-08-20","rating":-10.137,"rank":null,"conf_rank":null,"last_match":"L 84-137 vs. Spain (FIBA World Cup)","is_end_of_season":0,"is_game_day":1,"is_year_anchor":0,"year_anchor_label":"","tournament_finishes":[],"continental_winner":0},{"date":"1982-08-21","rating":-7.65,"rank":null,"conf_rank":null,"last_match":"L 76-143 vs. Russia (FIBA World Cup)","is_end_of_season":0,"is_game_day":1,"is_year_anchor":0,"year_anchor_label":"","tournament_finishes":[],"continental_winner":0},{"date":"1982-08-22","rating":-5.722,"rank":null,"conf_rank":null,"last_match":"L 83-100 vs. United States (FIBA World Cup)","is_end_of_season":0,"is_game_day":1,"is_year_anchor":0,"year_anchor_label":"","tournament_finishes":[],"continental_winner":0},{"date":"1982-08-23","rating":-6.223,"rank":null,"conf_rank":null,"last_match":"L 83-100 vs. United States (FIBA World Cup)","is_end_of_season":0,"is_game_day":1,"is_year_anchor":0,"year_anchor_label":"","tournament_finishes":[],"continental_winner":0},{"date":"1982-08-24","rating":-6.484,"rank":15,"conf_rank":7,"last_match":"L 63-72 vs. Australia (FIBA World Cup)","is_end_of_season":0,"is_game_day":1,"is_year_anchor":0,"year_anchor_label":"","tournament_finishes":[],"continental_winner":0},{"date":"1982-08-25","rating":-3.162,"rank":14,"conf_rank":7,"last_match":"L 88-97 vs. Yugoslavia (FIBA World Cup)","is_end_of_season":0,"is_game_day":1,"is_year_anchor":0,"year_anchor_label":"","tournament_finishes":[],"continental_winner":0},{"date":"1982-08-26","rating":-3.067,"rank":14,"conf_rank":7,"last_match":"L 88-97 vs. Yugoslavia (FIBA World Cup)","is_end_of_season":0,"is_game_day":1,"is_year_anchor":0,"year_anchor_label":"","tournament_finishes":[],"continental_winner":0},{"date":"1982-08-27","rating":-5.635,"rank":15,"conf_rank":7,"last_match":"L 79-107 vs. Canada (FIBA World Cup)","is_end_of_season":0,"is_game_day":1,"is_year_anchor":0,"year_anchor_label":"","tournament_finishes":[],"continental_winner":0},{"date":"1982-08-28","rating":-5.612,"rank":15,"conf_rank":7,"last_match":"L 79-107 vs. Canada (FIBA World Cup)","is_end_of_season":1,"is_game_day":1,"is_year_anchor":1,"year_anchor_label":"End of FIBA World Cup","tournament_finishes":[],"continental_winner":0}],"1984":[{"date":"1984-07-29","rating":-7.503,"rank":10,"conf_rank":5,"last_match":"L 79-107 vs. Canada (FIBA World Cup)","is_end_of_season":0,"is_game_day":1,"is_year_anchor":0,"year_anchor_label":"","tournament_finishes":[],"continental_winner":0},{"date":"1984-07-30","rating":-8.707,"rank":10,"conf_rank":5,"last_match":"L 79-107 vs. Canada (FIBA World Cup)","is_end_of_season":0,"is_game_day":1,"is_year_anchor":0,"year_anchor_label":"","tournament_finishes":[],"continental_winner":0},{"date":"1984-07-31","rating":-8.995,"rank":10,"conf_rank":5,"last_match":"L 79-107 vs. Canada (FIBA World Cup)","is_end_of_season":0,"is_game_day":1,"is_year_anchor":0,"year_anchor_label":"","tournament_finishes":[],"continental_winner":0},{"date":"1984-08-01","rating":-8.707,"rank":10,"conf_rank":5,"last_match":"L 79-107 vs. Canada (FIBA World Cup)","is_end_of_season":0,"is_game_day":1,"is_year_anchor":0,"year_anchor_label":"","tournament_finishes":[],"continental_winner":0},{"date":"1984-08-02","rating":-8.635,"rank":12,"conf_rank":5,"last_match":"L 79-107 vs. Canada (FIBA World Cup)","is_end_of_season":0,"is_game_day":1,"is_year_anchor":0,"year_anchor_label":"","tournament_finishes":[],"continental_winner":0},{"date":"1984-08-03","rating":-8.767,"rank":12,"conf_rank":5,"last_match":"L 79-107 vs. Canada (FIBA World Cup)","is_end_of_season":0,"is_game_day":1,"is_year_anchor":0,"year_anchor_label":"","tournament_finishes":[],"continental_winner":0},{"date":"1984-08-04","rating":-8.453,"rank":12,"conf_rank":5,"last_match":"L 79-107 vs. Canada (FIBA World Cup)","is_end_of_season":1,"is_game_day":1,"is_year_anchor":1,"year_anchor_label":"End of year","tournament_finishes":[],"continental_winner":0}],"1986":[{"date":"1986-07-05","rating":-7.572,"rank":13,"conf_rank":6,"last_match":"L 79-107 vs. Canada (FIBA World Cup)","is_end_of_season":0,"is_game_day":1,"is_year_anchor":0,"year_anchor_label":"","tournament_finishes":[],"continental_winner":0},{"date":"1986-07-06","rating":-7.541,"rank":14,"conf_rank":6,"last_match":"L 79-107 vs. Canada (FIBA World Cup)","is_end_of_season":0,"is_game_day":1,"is_year_anchor":0,"year_anchor_label":"","tournament_finishes":[],"continental_winner":0},{"date":"1986-07-07","rating":-5.41,"rank":14,"conf_rank":6,"last_match":"L 79-107 vs. Canada (FIBA World Cup)","is_end_of_season":0,"is_game_day":1,"is_year_anchor":0,"year_anchor_label":"","tournament_finishes":[],"continental_winner":0},{"date":"1986-07-08","rating":-5.109,"rank":13,"conf_rank":5,"last_match":"L 79-107 vs. Canada (FIBA World Cup)","is_end_of_season":0,"is_game_day":1,"is_year_anchor":0,"year_anchor_label":"","tournament_finishes":[],"continental_winner":0},{"date":"1986-07-09","rating":-5.015,"rank":20,"conf_rank":8,"last_match":"L 79-107 vs. Canada (FIBA World Cup)","is_end_of_season":0,"is_game_day":1,"is_year_anchor":0,"year_anchor_label":"","tournament_finishes":[],"continental_winner":0},{"date":"1986-07-10","rating":-5.093,"rank":20,"conf_rank":8,"last_match":"L 79-107 vs. Canada (FIBA World Cup)","is_end_of_season":0,"is_game_day":1,"is_year_anchor":0,"year_anchor_label":"","tournament_finishes":[],"continental_winner":0},{"date":"1986-07-13","rating":-5.525,"rank":20,"conf_rank":8,"last_match":"L 79-107 vs. Canada (FIBA World Cup)","is_end_of_season":0,"is_game_day":1,"is_year_anchor":0,"year_anchor_label":"","tournament_finishes":[],"continental_winner":0},{"date":"1986-07-14","rating":-5.387,"rank":20,"conf_rank":8,"last_match":"L 79-107 vs. Canada (FIBA World Cup)","is_end_of_season":0,"is_game_day":1,"is_year_anchor":0,"year_anchor_label":"","tournament_finishes":[],"continental_winner":0},{"date":"1986-07-15","rating":-5.547,"rank":20,"conf_rank":8,"last_match":"L 79-107 vs. Canada (FIBA World Cup)","is_end_of_season":0,"is_game_day":1,"is_year_anchor":0,"year_anchor_label":"","tournament_finishes":[],"continental_winner":0},{"date":"1986-07-17","rating":-5.526,"rank":20,"conf_rank":8,"last_match":"L 79-107 vs. Canada (FIBA World Cup)","is_end_of_season":0,"is_game_day":1,"is_year_anchor":0,"year_anchor_label":"","tournament_finishes":[],"continental_winner":0},{"date":"1986-07-18","rating":-5.524,"rank":20,"conf_rank":8,"last_match":"L 79-107 vs. Canada (FIBA World Cup)","is_end_of_season":0,"is_game_day":1,"is_year_anchor":0,"year_anchor_label":"","tournament_finishes":[],"continental_winner":0},{"date":"1986-07-19","rating":-5.604,"rank":20,"conf_rank":8,"last_match":"L 79-107 vs. Canada (FIBA World Cup)","is_end_of_season":0,"is_game_day":1,"is_year_anchor":0,"year_anchor_label":"","tournament_finishes":[],"continental_winner":0},{"date":"1986-07-20","rating":-5.404,"rank":20,"conf_rank":8,"last_match":"L 79-107 vs. Canada (FIBA World Cup)","is_end_of_season":1,"is_game_day":1,"is_year_anchor":1,"year_anchor_label":"End of year","tournament_finishes":[],"continental_winner":0}],"2017":[{"date":"2017-08-25","rating":11.544,"rank":null,"conf_rank":null,"last_match":"L 74-76 vs. Brazil (FIBA AmeriCup)","is_end_of_season":0,"is_game_day":1,"is_year_anchor":0,"year_anchor_label":"","tournament_finishes":[],"continental_winner":0},{"date":"2017-08-26","rating":-0.318,"rank":null,"conf_rank":null,"last_match":"L 72-91 vs. Puerto Rico (FIBA AmeriCup)","is_end_of_season":0,"is_game_day":1,"is_year_anchor":0,"year_anchor_label":"","tournament_finishes":[],"continental_winner":0},{"date":"2017-08-27","rating":0.805,"rank":null,"conf_rank":null,"last_match":"L 70-82 vs. Mexico (FIBA AmeriCup)","is_end_of_season":0,"is_game_day":1,"is_year_anchor":0,"year_anchor_label":"","tournament_finishes":[],"continental_winner":0},{"date":"2017-08-28","rating":0.412,"rank":null,"conf_rank":null,"last_match":"L 70-82 vs. Mexico (FIBA AmeriCup)","is_end_of_season":0,"is_game_day":1,"is_year_anchor":0,"year_anchor_label":"","tournament_finishes":[],"continental_winner":0},{"date":"2017-08-29","rating":0.944,"rank":null,"conf_rank":null,"last_match":"L 70-82 vs. Mexico (FIBA AmeriCup)","is_end_of_season":0,"is_game_day":1,"is_year_anchor":0,"year_anchor_label":"","tournament_finishes":[],"continental_winner":0},{"date":"2017-08-30","rating":1.047,"rank":null,"conf_rank":null,"last_match":"L 70-82 vs. Mexico (FIBA AmeriCup)","is_end_of_season":0,"is_game_day":1,"is_year_anchor":0,"year_anchor_label":"","tournament_finishes":[],"continental_winner":0},{"date":"2017-08-31","rating":0.987,"rank":null,"conf_rank":null,"last_match":"L 70-82 vs. Mexico (FIBA AmeriCup)","is_end_of_season":0,"is_game_day":1,"is_year_anchor":0,"year_anchor_label":"","tournament_finishes":[],"continental_winner":0},{"date":"2017-09-01","rating":0.906,"rank":null,"conf_rank":null,"last_match":"L 70-82 vs. Mexico (FIBA AmeriCup)","is_end_of_season":0,"is_game_day":1,"is_year_anchor":0,"year_anchor_label":"","tournament_finishes":[],"continental_winner":0},{"date":"2017-09-02","rating":0.329,"rank":null,"conf_rank":null,"last_match":"L 70-82 vs. Mexico (FIBA AmeriCup)","is_end_of_season":0,"is_game_day":1,"is_year_anchor":0,"year_anchor_label":"","tournament_finishes":[],"continental_winner":0},{"date":"2017-09-03","rating":0.647,"rank":null,"conf_rank":null,"last_match":"L 70-82 vs. Mexico (FIBA AmeriCup)","is_end_of_season":1,"is_game_day":1,"is_year_anchor":1,"year_anchor_label":"End of FIBA AmeriCup","tournament_finishes":[],"continental_winner":0},{"date":"2017-09-04","rating":0.536,"rank":null,"conf_rank":null,"last_match":"L 70-82 vs. Mexico (FIBA AmeriCup)","is_end_of_season":0,"is_game_day":1,"is_year_anchor":0,"year_anchor_label":"","tournament_finishes":[],"continental_winner":0},{"date":"2017-09-05","rating":0.528,"rank":null,"conf_rank":null,"last_match":"L 70-82 vs. Mexico (FIBA AmeriCup)","is_end_of_season":0,"is_game_day":1,"is_year_anchor":0,"year_anchor_label":"","tournament_finishes":[],"continental_winner":0},{"date":"2017-09-06","rating":0.863,"rank":null,"conf_rank":null,"last_match":"L 70-82 vs. Mexico (FIBA AmeriCup)","is_end_of_season":0,"is_game_day":1,"is_year_anchor":0,"year_anchor_label":"","tournament_finishes":[],"continental_winner":0},{"date":"2017-09-07","rating":1.172,"rank":null,"conf_rank":null,"last_match":"L 70-82 vs. Mexico (FIBA AmeriCup)","is_end_of_season":0,"is_game_day":1,"is_year_anchor":0,"year_anchor_label":"","tournament_finishes":[],"continental_winner":0},{"date":"2017-09-08","rating":0.847,"rank":null,"conf_rank":null,"last_match":"L 70-82 vs. Mexico (FIBA AmeriCup)","is_end_of_season":0,"is_game_day":1,"is_year_anchor":0,"year_anchor_label":"","tournament_finishes":[],"continental_winner":0},{"date":"2017-09-09","rating":1.371,"rank":null,"conf_rank":null,"last_match":"L 70-82 vs. Mexico (FIBA AmeriCup)","is_end_of_season":0,"is_game_day":1,"is_year_anchor":0,"year_anchor_label":"","tournament_finishes":[],"continental_winner":0},{"date":"2017-09-10","rating":0.563,"rank":null,"conf_rank":null,"last_match":"L 70-82 vs. Mexico (FIBA AmeriCup)","is_end_of_season":0,"is_game_day":1,"is_year_anchor":0,"year_anchor_label":"","tournament_finishes":[],"continental_winner":0},{"date":"2017-09-12","rating":0.538,"rank":null,"conf_rank":null,"last_match":"L 70-82 vs. Mexico (FIBA AmeriCup)","is_end_of_season":0,"is_game_day":1,"is_year_anchor":0,"year_anchor_label":"","tournament_finishes":[],"continental_winner":0},{"date":"2017-09-13","rating":0.541,"rank":null,"conf_rank":null,"last_match":"L 70-82 vs. Mexico (FIBA AmeriCup)","is_end_of_season":0,"is_game_day":1,"is_year_anchor":0,"year_anchor_label":"","tournament_finishes":[],"continental_winner":0},{"date":"2017-09-14","rating":0.545,"rank":null,"conf_rank":null,"last_match":"L 70-82 vs. Mexico (FIBA AmeriCup)","is_end_of_season":0,"is_game_day":1,"is_year_anchor":0,"year_anchor_label":"","tournament_finishes":[],"continental_winner":0},{"date":"2017-09-15","rating":0.599,"rank":null,"conf_rank":null,"last_match":"L 70-82 vs. Mexico (FIBA AmeriCup)","is_end_of_season":0,"is_game_day":1,"is_year_anchor":0,"year_anchor_label":"","tournament_finishes":[],"continental_winner":0},{"date":"2017-09-16","rating":0.511,"rank":null,"conf_rank":null,"last_match":"L 70-82 vs. Mexico (FIBA AmeriCup)","is_end_of_season":1,"is_game_day":1,"is_year_anchor":0,"year_anchor_label":"","tournament_finishes":[],"continental_winner":0},{"date":"2017-09-17","rating":0.489,"rank":null,"conf_rank":null,"last_match":"L 70-82 vs. Mexico (FIBA AmeriCup)","is_end_of_season":1,"is_game_day":1,"is_year_anchor":0,"year_anchor_label":"","tournament_finishes":[],"continental_winner":0},{"date":"2017-11-23","rating":0.818,"rank":null,"conf_rank":null,"last_match":"L 70-82 vs. Mexico (FIBA AmeriCup)","is_end_of_season":0,"is_game_day":1,"is_year_anchor":0,"year_anchor_label":"","tournament_finishes":[],"continental_winner":0},{"date":"2017-11-24","rating":-1.142,"rank":52,"conf_rank":11,"last_match":"L 71-85 vs. Venezuela (WC Qualifiers)","is_end_of_season":0,"is_game_day":1,"is_year_anchor":0,"year_anchor_label":"","tournament_finishes":[],"continental_winner":0},{"date":"2017-11-25","rating":-1.073,"rank":52,"conf_rank":11,"last_match":"L 71-85 vs. Venezuela (WC Qualifiers)","is_end_of_season":0,"is_game_day":1,"is_year_anchor":0,"year_anchor_label":"","tournament_finishes":[],"continental_winner":0},{"date":"2017-11-26","rating":-0.986,"rank":53,"conf_rank":12,"last_match":"L 71-85 vs. Venezuela (WC Qualifiers)","is_end_of_season":0,"is_game_day":1,"is_year_anchor":0,"year_anchor_label":"","tournament_finishes":[],"continental_winner":0},{"date":"2017-11-27","rating":-1.842,"rank":56,"conf_rank":12,"last_match":"L 69-74 vs. Chile (WC Qualifiers)","is_end_of_season":0,"is_game_day":1,"is_year_anchor":0,"year_anchor_label":"","tournament_finishes":[],"continental_winner":0}],"2018":[{"date":"2018-02-22","rating":-4.521,"rank":61,"conf_rank":12,"last_match":"L 49-84 vs. Brazil (WC Qualifiers)","is_end_of_season":0,"is_game_day":1,"is_year_anchor":0,"year_anchor_label":"","tournament_finishes":[],"continental_winner":0},{"date":"2018-02-23","rating":-4.605,"rank":63,"conf_rank":12,"last_match":"L 49-84 vs. Brazil (WC Qualifiers)","is_end_of_season":0,"is_game_day":1,"is_year_anchor":0,"year_anchor_label":"","tournament_finishes":[],"continental_winner":0},{"date":"2018-02-24","rating":-4.528,"rank":62,"conf_rank":12,"last_match":"L 49-84 vs. Brazil (WC Qualifiers)","is_end_of_season":0,"is_game_day":1,"is_year_anchor":0,"year_anchor_label":"","tournament_finishes":[],"continental_winner":0},{"date":"2018-02-25","rating":-5.361,"rank":63,"conf_rank":13,"last_match":"L 62-73 vs. Venezuela (WC Qualifiers)","is_end_of_season":0,"is_game_day":1,"is_year_anchor":0,"year_anchor_label":"","tournament_finishes":[],"continental_winner":0},{"date":"2018-02-26","rating":-5.132,"rank":62,"conf_rank":12,"last_match":"L 62-73 vs. Venezuela (WC Qualifiers)","is_end_of_season":0,"is_game_day":1,"is_year_anchor":0,"year_anchor_label":"","tournament_finishes":[],"continental_winner":0},{"date":"2018-06-28","rating":-4.951,"rank":63,"conf_rank":13,"last_match":"L 62-73 vs. Venezuela (WC Qualifiers)","is_end_of_season":0,"is_game_day":1,"is_year_anchor":0,"year_anchor_label":"","tournament_finishes":[],"continental_winner":0},{"date":"2018-06-29","rating":-4.642,"rank":63,"conf_rank":13,"last_match":"W 71-67 vs. Chile (WC Qualifiers)","is_end_of_season":0,"is_game_day":1,"is_year_anchor":0,"year_anchor_label":"","tournament_finishes":[],"continental_winner":0},{"date":"2018-06-30","rating":-4.554,"rank":63,"conf_rank":13,"last_match":"W 71-67 vs. Chile (WC Qualifiers)","is_end_of_season":0,"is_game_day":1,"is_year_anchor":0,"year_anchor_label":"","tournament_finishes":[],"continental_winner":0},{"date":"2018-07-01","rating":-4.397,"rank":63,"conf_rank":13,"last_match":"W 71-67 vs. Chile (WC Qualifiers)","is_end_of_season":0,"is_game_day":1,"is_year_anchor":0,"year_anchor_label":"","tournament_finishes":[],"continental_winner":0},{"date":"2018-07-02","rating":-5.792,"rank":66,"conf_rank":14,"last_match":"L 71-98 vs. Brazil (WC Qualifiers)","is_end_of_season":0,"is_game_day":1,"is_year_anchor":0,"year_anchor_label":"","tournament_finishes":[],"continental_winner":0},{"date":"2018-09-13","rating":-5.6,"rank":65,"conf_rank":14,"last_match":"L 71-98 vs. Brazil (WC Qualifiers)","is_end_of_season":0,"is_game_day":1,"is_year_anchor":0,"year_anchor_label":"","tournament_finishes":[],"continental_winner":0},{"date":"2018-09-14","rating":-6.031,"rank":65,"conf_rank":14,"last_match":"L 71-98 vs. Brazil (WC Qualifiers)","is_end_of_season":0,"is_game_day":1,"is_year_anchor":0,"year_anchor_label":"","tournament_finishes":[],"continental_winner":0},{"date":"2018-09-15","rating":-5.922,"rank":65,"conf_rank":14,"last_match":"L 71-98 vs. Brazil (WC Qualifiers)","is_end_of_season":0,"is_game_day":1,"is_year_anchor":0,"year_anchor_label":"","tournament_finishes":[],"continental_winner":0},{"date":"2018-09-16","rating":-5.592,"rank":65,"conf_rank":14,"last_match":"L 71-98 vs. Brazil (WC Qualifiers)","is_end_of_season":0,"is_game_day":1,"is_year_anchor":0,"year_anchor_label":"","tournament_finishes":[],"continental_winner":0},{"date":"2018-09-17","rating":-6.092,"rank":65,"conf_rank":14,"last_match":"L 71-98 vs. Brazil (WC Qualifiers)","is_end_of_season":0,"is_game_day":1,"is_year_anchor":0,"year_anchor_label":"","tournament_finishes":[],"continental_winner":0},{"date":"2018-11-29","rating":-6.39,"rank":65,"conf_rank":14,"last_match":"L 71-98 vs. Brazil (WC Qualifiers)","is_end_of_season":0,"is_game_day":1,"is_year_anchor":0,"year_anchor_label":"","tournament_finishes":[],"continental_winner":0},{"date":"2018-11-30","rating":-5.553,"rank":63,"conf_rank":13,"last_match":"L 71-98 vs. Brazil (WC Qualifiers)","is_end_of_season":0,"is_game_day":1,"is_year_anchor":0,"year_anchor_label":"","tournament_finishes":[],"continental_winner":0},{"date":"2018-12-01","rating":-5.561,"rank":63,"conf_rank":13,"last_match":"L 71-98 vs. Brazil (WC Qualifiers)","is_end_of_season":0,"is_game_day":1,"is_year_anchor":0,"year_anchor_label":"","tournament_finishes":[],"continental_winner":0},{"date":"2018-12-02","rating":-5.588,"rank":63,"conf_rank":13,"last_match":"L 71-98 vs. Brazil (WC Qualifiers)","is_end_of_season":0,"is_game_day":1,"is_year_anchor":0,"year_anchor_label":"","tournament_finishes":[],"continental_winner":0},{"date":"2018-12-03","rating":-5.533,"rank":63,"conf_rank":13,"last_match":"L 71-98 vs. Brazil (WC Qualifiers)","is_end_of_season":0,"is_game_day":1,"is_year_anchor":1,"year_anchor_label":"End of year","tournament_finishes":[],"continental_winner":0}],"2019":[{"date":"2019-02-21","rating":-5.779,"rank":63,"conf_rank":13,"last_match":"L 71-98 vs. Brazil (WC Qualifiers)","is_end_of_season":0,"is_game_day":1,"is_year_anchor":0,"year_anchor_label":"","tournament_finishes":[],"continental_winner":0},{"date":"2019-02-22","rating":-6.439,"rank":65,"conf_rank":13,"last_match":"L 71-98 vs. Brazil (WC Qualifiers)","is_end_of_season":0,"is_game_day":1,"is_year_anchor":0,"year_anchor_label":"","tournament_finishes":[],"continental_winner":0},{"date":"2019-02-23","rating":-6.441,"rank":65,"conf_rank":13,"last_match":"L 71-98 vs. Brazil (WC Qualifiers)","is_end_of_season":0,"is_game_day":1,"is_year_anchor":0,"year_anchor_label":"","tournament_finishes":[],"continental_winner":0},{"date":"2019-02-24","rating":-6.791,"rank":65,"conf_rank":13,"last_match":"L 71-98 vs. Brazil (WC Qualifiers)","is_end_of_season":0,"is_game_day":1,"is_year_anchor":0,"year_anchor_label":"","tournament_finishes":[],"continental_winner":0},{"date":"2019-02-25","rating":-6.684,"rank":64,"conf_rank":13,"last_match":"L 71-98 vs. Brazil (WC Qualifiers)","is_end_of_season":0,"is_game_day":1,"is_year_anchor":0,"year_anchor_label":"","tournament_finishes":[],"continental_winner":0},{"date":"2019-08-01","rating":-7.749,"rank":67,"conf_rank":13,"last_match":"L 71-98 vs. Brazil (WC Qualifiers)","is_end_of_season":0,"is_game_day":1,"is_year_anchor":0,"year_anchor_label":"","tournament_finishes":[],"continental_winner":0},{"date":"2019-08-31","rating":-7.237,"rank":65,"conf_rank":13,"last_match":"L 71-98 vs. Brazil (WC Qualifiers)","is_end_of_season":0,"is_game_day":1,"is_year_anchor":0,"year_anchor_label":"","tournament_finishes":[],"continental_winner":0},{"date":"2019-09-01","rating":-7.545,"rank":65,"conf_rank":13,"last_match":"L 71-98 vs. Brazil (WC Qualifiers)","is_end_of_season":0,"is_game_day":1,"is_year_anchor":0,"year_anchor_label":"","tournament_finishes":[],"continental_winner":0},{"date":"2019-09-02","rating":-7.444,"rank":65,"conf_rank":13,"last_match":"L 71-98 vs. Brazil (WC Qualifiers)","is_end_of_season":0,"is_game_day":1,"is_year_anchor":0,"year_anchor_label":"","tournament_finishes":[],"continental_winner":0},{"date":"2019-09-03","rating":-6.879,"rank":65,"conf_rank":13,"last_match":"L 71-98 vs. Brazil (WC Qualifiers)","is_end_of_season":0,"is_game_day":1,"is_year_anchor":0,"year_anchor_label":"","tournament_finishes":[],"continental_winner":0},{"date":"2019-09-04","rating":-6.41,"rank":65,"conf_rank":13,"last_match":"L 71-98 vs. Brazil (WC Qualifiers)","is_end_of_season":0,"is_game_day":1,"is_year_anchor":0,"year_anchor_label":"","tournament_finishes":[],"continental_winner":0},{"date":"2019-09-05","rating":-5.837,"rank":63,"conf_rank":13,"last_match":"L 71-98 vs. Brazil (WC Qualifiers)","is_end_of_season":0,"is_game_day":1,"is_year_anchor":0,"year_anchor_label":"","tournament_finishes":[],"continental_winner":0},{"date":"2019-09-06","rating":-6.317,"rank":65,"conf_rank":13,"last_match":"L 71-98 vs. Brazil (WC Qualifiers)","is_end_of_season":0,"is_game_day":1,"is_year_anchor":0,"year_anchor_label":"","tournament_finishes":[],"continental_winner":0},{"date":"2019-09-07","rating":-6.968,"rank":66,"conf_rank":13,"last_match":"L 71-98 vs. Brazil (WC Qualifiers)","is_end_of_season":0,"is_game_day":1,"is_year_anchor":0,"year_anchor_label":"","tournament_finishes":[],"continental_winner":0},{"date":"2019-09-08","rating":-6.677,"rank":67,"conf_rank":14,"last_match":"L 71-98 vs. Brazil (WC Qualifiers)","is_end_of_season":0,"is_game_day":1,"is_year_anchor":0,"year_anchor_label":"","tournament_finishes":[],"continental_winner":0},{"date":"2019-09-09","rating":-6.907,"rank":67,"conf_rank":14,"last_match":"L 71-98 vs. Brazil (WC Qualifiers)","is_end_of_season":0,"is_game_day":1,"is_year_anchor":0,"year_anchor_label":"","tournament_finishes":[],"continental_winner":0},{"date":"2019-09-10","rating":-6.811,"rank":67,"conf_rank":14,"last_match":"L 71-98 vs. Brazil (WC Qualifiers)","is_end_of_season":0,"is_game_day":1,"is_year_anchor":0,"year_anchor_label":"","tournament_finishes":[],"continental_winner":0},{"date":"2019-09-11","rating":-6.836,"rank":67,"conf_rank":14,"last_match":"L 71-98 vs. Brazil (WC Qualifiers)","is_end_of_season":0,"is_game_day":1,"is_year_anchor":0,"year_anchor_label":"","tournament_finishes":[],"continental_winner":0},{"date":"2019-09-12","rating":-6.896,"rank":67,"conf_rank":14,"last_match":"L 71-98 vs. Brazil (WC Qualifiers)","is_end_of_season":0,"is_game_day":1,"is_year_anchor":0,"year_anchor_label":"","tournament_finishes":[],"continental_winner":0},{"date":"2019-09-13","rating":-6.801,"rank":67,"conf_rank":14,"last_match":"L 71-98 vs. Brazil (WC Qualifiers)","is_end_of_season":0,"is_game_day":1,"is_year_anchor":0,"year_anchor_label":"","tournament_finishes":[],"continental_winner":0},{"date":"2019-09-14","rating":-6.802,"rank":67,"conf_rank":14,"last_match":"L 71-98 vs. Brazil (WC Qualifiers)","is_end_of_season":0,"is_game_day":1,"is_year_anchor":0,"year_anchor_label":"","tournament_finishes":[],"continental_winner":0},{"date":"2019-09-15","rating":-6.97,"rank":67,"conf_rank":14,"last_match":"L 71-98 vs. Brazil (WC Qualifiers)","is_end_of_season":1,"is_game_day":1,"is_year_anchor":1,"year_anchor_label":"End of year","tournament_finishes":[],"continental_winner":0}],"2021":[{"date":"2021-04-15","rating":-8.443,"rank":67,"conf_rank":14,"last_match":"L 71-98 vs. Brazil (WC Qualifiers)","is_end_of_season":0,"is_game_day":1,"is_year_anchor":0,"year_anchor_label":"","tournament_finishes":[],"continental_winner":0},{"date":"2021-04-16","rating":-8.436,"rank":67,"conf_rank":14,"last_match":"L 71-98 vs. Brazil (WC Qualifiers)","is_end_of_season":0,"is_game_day":1,"is_year_anchor":0,"year_anchor_label":"","tournament_finishes":[],"continental_winner":0},{"date":"2021-04-17","rating":-8.429,"rank":67,"conf_rank":14,"last_match":"L 71-98 vs. Brazil (WC Qualifiers)","is_end_of_season":0,"is_game_day":1,"is_year_anchor":0,"year_anchor_label":"","tournament_finishes":[],"continental_winner":0},{"date":"2021-04-18","rating":-8.423,"rank":68,"conf_rank":15,"last_match":"L 71-98 vs. Brazil (WC Qualifiers)","is_end_of_season":0,"is_game_day":1,"is_year_anchor":0,"year_anchor_label":"","tournament_finishes":[],"continental_winner":0},{"date":"2021-04-19","rating":-8.416,"rank":72,"conf_rank":19,"last_match":"L 71-98 vs. Brazil (WC Qualifiers)","is_end_of_season":0,"is_game_day":1,"is_year_anchor":0,"year_anchor_label":"","tournament_finishes":[],"continental_winner":0},{"date":"2021-06-12","rating":-8.13,"rank":72,"conf_rank":19,"last_match":"L 71-98 vs. Brazil (WC Qualifiers)","is_end_of_season":0,"is_game_day":1,"is_year_anchor":0,"year_anchor_label":"","tournament_finishes":[],"continental_winner":0},{"date":"2021-06-16","rating":-8.108,"rank":72,"conf_rank":19,"last_match":"L 71-98 vs. Brazil (WC Qualifiers)","is_end_of_season":0,"is_game_day":1,"is_year_anchor":0,"year_anchor_label":"","tournament_finishes":[],"continental_winner":0},{"date":"2021-07-02","rating":-8.007,"rank":72,"conf_rank":20,"last_match":"L 71-98 vs. Brazil (WC Qualifiers)","is_end_of_season":0,"is_game_day":1,"is_year_anchor":0,"year_anchor_label":"","tournament_finishes":[],"continental_winner":0},{"date":"2021-07-03","rating":-6.436,"rank":66,"conf_rank":14,"last_match":"L 71-98 vs. Brazil (WC Qualifiers)","is_end_of_season":0,"is_game_day":1,"is_year_anchor":0,"year_anchor_label":"","tournament_finishes":[],"continental_winner":0},{"date":"2021-07-04","rating":-6.613,"rank":66,"conf_rank":14,"last_match":"L 71-98 vs. Brazil (WC Qualifiers)","is_end_of_season":0,"is_game_day":1,"is_year_anchor":0,"year_anchor_label":"","tournament_finishes":[],"continental_winner":0},{"date":"2021-07-13","rating":-5.959,"rank":66,"conf_rank":14,"last_match":"L 71-98 vs. Brazil (WC Qualifiers)","is_end_of_season":0,"is_game_day":1,"is_year_anchor":0,"year_anchor_label":"","tournament_finishes":[],"continental_winner":0},{"date":"2021-07-14","rating":-5.335,"rank":64,"conf_rank":14,"last_match":"L 71-98 vs. Brazil (WC Qualifiers)","is_end_of_season":0,"is_game_day":1,"is_year_anchor":0,"year_anchor_label":"","tournament_finishes":[],"continental_winner":0},{"date":"2021-07-15","rating":-5.028,"rank":64,"conf_rank":14,"last_match":"L 71-98 vs. Brazil (WC Qualifiers)","is_end_of_season":0,"is_game_day":1,"is_year_anchor":0,"year_anchor_label":"","tournament_finishes":[],"continental_winner":0},{"date":"2021-07-25","rating":-4.988,"rank":64,"conf_rank":14,"last_match":"L 71-98 vs. Brazil (WC Qualifiers)","is_end_of_season":0,"is_game_day":1,"is_year_anchor":0,"year_anchor_label":"","tournament_finishes":[],"continental_winner":0},{"date":"2021-07-26","rating":-5.737,"rank":64,"conf_rank":13,"last_match":"L 71-98 vs. Brazil (WC Qualifiers)","is_end_of_season":0,"is_game_day":1,"is_year_anchor":0,"year_anchor_label":"","tournament_finishes":[],"continental_winner":0},{"date":"2021-07-28","rating":-5.577,"rank":65,"conf_rank":14,"last_match":"L 71-98 vs. Brazil (WC Qualifiers)","is_end_of_season":0,"is_game_day":1,"is_year_anchor":0,"year_anchor_label":"","tournament_finishes":[],"continental_winner":0},{"date":"2021-07-29","rating":-5.718,"rank":65,"conf_rank":14,"last_match":"L 71-98 vs. Brazil (WC Qualifiers)","is_end_of_season":0,"is_game_day":1,"is_year_anchor":0,"year_anchor_label":"","tournament_finishes":[],"continental_winner":0},{"date":"2021-07-31","rating":-5.519,"rank":65,"conf_rank":14,"last_match":"L 71-98 vs. Brazil (WC Qualifiers)","is_end_of_season":0,"is_game_day":1,"is_year_anchor":0,"year_anchor_label":"","tournament_finishes":[],"continental_winner":0},{"date":"2021-08-01","rating":-5.462,"rank":65,"conf_rank":14,"last_match":"L 71-98 vs. Brazil (WC Qualifiers)","is_end_of_season":0,"is_game_day":1,"is_year_anchor":0,"year_anchor_label":"","tournament_finishes":[],"continental_winner":0},{"date":"2021-08-03","rating":-5.853,"rank":63,"conf_rank":14,"last_match":"L 71-98 vs. Brazil (WC Qualifiers)","is_end_of_season":0,"is_game_day":1,"is_year_anchor":0,"year_anchor_label":"","tournament_finishes":[],"continental_winner":0},{"date":"2021-08-05","rating":-5.499,"rank":63,"conf_rank":14,"last_match":"L 71-98 vs. Brazil (WC Qualifiers)","is_end_of_season":0,"is_game_day":1,"is_year_anchor":0,"year_anchor_label":"","tournament_finishes":[],"continental_winner":0},{"date":"2021-08-07","rating":-5.441,"rank":63,"conf_rank":14,"last_match":"L 71-98 vs. Brazil (WC Qualifiers)","is_end_of_season":1,"is_game_day":1,"is_year_anchor":0,"year_anchor_label":"","tournament_finishes":[],"continental_winner":0},{"date":"2021-08-24","rating":-5.653,"rank":60,"conf_rank":14,"last_match":"L 71-98 vs. Brazil (WC Qualifiers)","is_end_of_season":0,"is_game_day":1,"is_year_anchor":0,"year_anchor_label":"","tournament_finishes":[],"continental_winner":0},{"date":"2021-08-25","rating":-7.756,"rank":64,"conf_rank":15,"last_match":"L 71-98 vs. Brazil (WC Qualifiers)","is_end_of_season":0,"is_game_day":1,"is_year_anchor":0,"year_anchor_label":"","tournament_finishes":[],"continental_winner":0},{"date":"2021-08-26","rating":-7.443,"rank":64,"conf_rank":14,"last_match":"L 71-98 vs. Brazil (WC Qualifiers)","is_end_of_season":0,"is_game_day":1,"is_year_anchor":0,"year_anchor_label":"","tournament_finishes":[],"continental_winner":0},{"date":"2021-08-27","rating":-7.559,"rank":62,"conf_rank":15,"last_match":"L 71-98 vs. Brazil (WC Qualifiers)","is_end_of_season":0,"is_game_day":1,"is_year_anchor":0,"year_anchor_label":"","tournament_finishes":[],"continental_winner":0},{"date":"2021-08-28","rating":-7.475,"rank":61,"conf_rank":15,"last_match":"L 71-98 vs. Brazil (WC Qualifiers)","is_end_of_season":0,"is_game_day":1,"is_year_anchor":0,"year_anchor_label":"","tournament_finishes":[],"continental_winner":0},{"date":"2021-08-29","rating":-7.371,"rank":61,"conf_rank":15,"last_match":"L 71-98 vs. Brazil (WC Qualifiers)","is_end_of_season":0,"is_game_day":1,"is_year_anchor":0,"year_anchor_label":"","tournament_finishes":[],"continental_winner":0},{"date":"2021-08-30","rating":-7.407,"rank":61,"conf_rank":15,"last_match":"L 71-98 vs. Brazil (WC Qualifiers)","is_end_of_season":0,"is_game_day":1,"is_year_anchor":0,"year_anchor_label":"","tournament_finishes":[],"continental_winner":0},{"date":"2021-08-31","rating":-7.682,"rank":64,"conf_rank":15,"last_match":"L 71-98 vs. Brazil (WC Qualifiers)","is_end_of_season":0,"is_game_day":1,"is_year_anchor":0,"year_anchor_label":"","tournament_finishes":[],"continental_winner":0},{"date":"2021-09-01","rating":-7.548,"rank":63,"conf_rank":15,"last_match":"L 71-98 vs. Brazil (WC Qualifiers)","is_end_of_season":0,"is_game_day":1,"is_year_anchor":0,"year_anchor_label":"","tournament_finishes":[],"continental_winner":0},{"date":"2021-09-02","rating":-7.792,"rank":64,"conf_rank":15,"last_match":"L 71-98 vs. Brazil (WC Qualifiers)","is_end_of_season":0,"is_game_day":1,"is_year_anchor":0,"year_anchor_label":"","tournament_finishes":[],"continental_winner":0},{"date":"2021-09-04","rating":-7.666,"rank":62,"conf_rank":14,"last_match":"L 71-98 vs. Brazil (WC Qualifiers)","is_end_of_season":0,"is_game_day":1,"is_year_anchor":0,"year_anchor_label":"","tournament_finishes":[],"continental_winner":0},{"date":"2021-09-05","rating":-7.614,"rank":62,"conf_rank":14,"last_match":"L 71-98 vs. Brazil (WC Qualifiers)","is_end_of_season":1,"is_game_day":1,"is_year_anchor":0,"year_anchor_label":"","tournament_finishes":[],"continental_winner":0},{"date":"2021-11-25","rating":-8.614,"rank":63,"conf_rank":14,"last_match":"L 71-98 vs. Brazil (WC Qualifiers)","is_end_of_season":0,"is_game_day":1,"is_year_anchor":0,"year_anchor_label":"","tournament_finishes":[],"continental_winner":0},{"date":"2021-11-26","rating":-4.378,"rank":55,"conf_rank":11,"last_match":"L 75-83 vs. Uruguay (WC Qualifiers)","is_end_of_season":0,"is_game_day":1,"is_year_anchor":0,"year_anchor_label":"","tournament_finishes":[],"continental_winner":0},{"date":"2021-11-27","rating":-5.968,"rank":57,"conf_rank":11,"last_match":"L 69-82 vs. Uruguay (WC Qualifiers)","is_end_of_season":0,"is_game_day":1,"is_year_anchor":0,"year_anchor_label":"","tournament_finishes":[],"continental_winner":0},{"date":"2021-11-28","rating":-6.384,"rank":59,"conf_rank":14,"last_match":"L 69-82 vs. Uruguay (WC Qualifiers)","is_end_of_season":0,"is_game_day":1,"is_year_anchor":0,"year_anchor_label":"","tournament_finishes":[],"continental_winner":0},{"date":"2021-11-29","rating":-4.994,"rank":56,"conf_rank":12,"last_match":"L 69-82 vs. Uruguay (WC Qualifiers)","is_end_of_season":0,"is_game_day":1,"is_year_anchor":1,"year_anchor_label":"End of year","tournament_finishes":[],"continental_winner":0}],"2022":[{"date":"2022-02-24","rating":-5.589,"rank":56,"conf_rank":13,"last_match":"L 69-82 vs. Uruguay (WC Qualifiers)","is_end_of_season":0,"is_game_day":1,"is_year_anchor":0,"year_anchor_label":"","tournament_finishes":[],"continental_winner":0},{"date":"2022-02-25","rating":-12.267,"rank":64,"conf_rank":15,"last_match":"L 76-90 vs. Chile (WC Qualifiers)","is_end_of_season":0,"is_game_day":1,"is_year_anchor":0,"year_anchor_label":"","tournament_finishes":[],"continental_winner":0},{"date":"2022-02-26","rating":-12.009,"rank":65,"conf_rank":15,"last_match":"L 76-90 vs. Chile (WC Qualifiers)","is_end_of_season":0,"is_game_day":1,"is_year_anchor":0,"year_anchor_label":"","tournament_finishes":[],"continental_winner":0},{"date":"2022-02-27","rating":-12.253,"rank":70,"conf_rank":15,"last_match":"L 76-90 vs. Chile (WC Qualifiers)","is_end_of_season":0,"is_game_day":1,"is_year_anchor":0,"year_anchor_label":"","tournament_finishes":[],"continental_winner":0},{"date":"2022-02-28","rating":-11.703,"rank":70,"conf_rank":15,"last_match":"L 73-119 vs. Brazil (WC Qualifiers)","is_end_of_season":0,"is_game_day":1,"is_year_anchor":0,"year_anchor_label":"","tournament_finishes":[],"continental_winner":0},{"date":"2022-06-30","rating":-10.884,"rank":70,"conf_rank":15,"last_match":"W 67-66 vs. Chile (WC Qualifiers)","is_end_of_season":0,"is_game_day":1,"is_year_anchor":0,"year_anchor_label":"","tournament_finishes":[],"continental_winner":0},{"date":"2022-07-01","rating":-11.457,"rank":69,"conf_rank":14,"last_match":"W 67-66 vs. Chile (WC Qualifiers)","is_end_of_season":0,"is_game_day":1,"is_year_anchor":0,"year_anchor_label":"","tournament_finishes":[],"continental_winner":0},{"date":"2022-07-02","rating":-12.09,"rank":69,"conf_rank":14,"last_match":"W 67-66 vs. Chile (WC Qualifiers)","is_end_of_season":0,"is_game_day":1,"is_year_anchor":0,"year_anchor_label":"","tournament_finishes":[],"continental_winner":0},{"date":"2022-07-03","rating":-6.183,"rank":60,"conf_rank":13,"last_match":"W 104-98 vs. Brazil (WC Qualifiers)","is_end_of_season":0,"is_game_day":1,"is_year_anchor":0,"year_anchor_label":"","tournament_finishes":[],"continental_winner":0},{"date":"2022-07-04","rating":-6.007,"rank":61,"conf_rank":13,"last_match":"W 104-98 vs. Brazil (WC Qualifiers)","is_end_of_season":0,"is_game_day":1,"is_year_anchor":0,"year_anchor_label":"","tournament_finishes":[],"continental_winner":0},{"date":"2022-07-07","rating":-6.017,"rank":61,"conf_rank":13,"last_match":"W 104-98 vs. Brazil (WC Qualifiers)","is_end_of_season":0,"is_game_day":1,"is_year_anchor":0,"year_anchor_label":"","tournament_finishes":[],"continental_winner":0},{"date":"2022-07-12","rating":-6.107,"rank":61,"conf_rank":13,"last_match":"W 104-98 vs. Brazil (WC Qualifiers)","is_end_of_season":0,"is_game_day":1,"is_year_anchor":0,"year_anchor_label":"","tournament_finishes":[],"continental_winner":0},{"date":"2022-07-13","rating":-6.142,"rank":60,"conf_rank":13,"last_match":"W 104-98 vs. Brazil (WC Qualifiers)","is_end_of_season":0,"is_game_day":1,"is_year_anchor":0,"year_anchor_label":"","tournament_finishes":[],"continental_winner":0},{"date":"2022-07-14","rating":-6.225,"rank":60,"conf_rank":13,"last_match":"W 104-98 vs. Brazil (WC Qualifiers)","is_end_of_season":0,"is_game_day":1,"is_year_anchor":0,"year_anchor_label":"","tournament_finishes":[],"continental_winner":0},{"date":"2022-07-15","rating":-6.457,"rank":61,"conf_rank":13,"last_match":"W 104-98 vs. Brazil (WC Qualifiers)","is_end_of_season":0,"is_game_day":1,"is_year_anchor":0,"year_anchor_label":"","tournament_finishes":[],"continental_winner":0},{"date":"2022-07-16","rating":-6.446,"rank":60,"conf_rank":13,"last_match":"W 104-98 vs. Brazil (WC Qualifiers)","is_end_of_season":0,"is_game_day":1,"is_year_anchor":0,"year_anchor_label":"","tournament_finishes":[],"continental_winner":0},{"date":"2022-07-17","rating":-6.384,"rank":60,"conf_rank":13,"last_match":"W 104-98 vs. Brazil (WC Qualifiers)","is_end_of_season":0,"is_game_day":1,"is_year_anchor":0,"year_anchor_label":"","tournament_finishes":[],"continental_winner":0},{"date":"2022-07-18","rating":-6.425,"rank":60,"conf_rank":13,"last_match":"W 104-98 vs. Brazil (WC Qualifiers)","is_end_of_season":0,"is_game_day":1,"is_year_anchor":0,"year_anchor_label":"","tournament_finishes":[],"continental_winner":0},{"date":"2022-07-19","rating":-6.382,"rank":60,"conf_rank":13,"last_match":"W 104-98 vs. Brazil (WC Qualifiers)","is_end_of_season":0,"is_game_day":1,"is_year_anchor":0,"year_anchor_label":"","tournament_finishes":[],"continental_winner":0},{"date":"2022-07-20","rating":-6.436,"rank":60,"conf_rank":13,"last_match":"W 104-98 vs. Brazil (WC Qualifiers)","is_end_of_season":0,"is_game_day":1,"is_year_anchor":0,"year_anchor_label":"","tournament_finishes":[],"continental_winner":0},{"date":"2022-07-21","rating":-6.392,"rank":60,"conf_rank":13,"last_match":"W 104-98 vs. Brazil (WC Qualifiers)","is_end_of_season":0,"is_game_day":1,"is_year_anchor":0,"year_anchor_label":"","tournament_finishes":[],"continental_winner":0},{"date":"2022-07-23","rating":-6.364,"rank":60,"conf_rank":13,"last_match":"W 104-98 vs. Brazil (WC Qualifiers)","is_end_of_season":0,"is_game_day":1,"is_year_anchor":0,"year_anchor_label":"","tournament_finishes":[],"continental_winner":0},{"date":"2022-07-24","rating":-6.383,"rank":60,"conf_rank":13,"last_match":"W 104-98 vs. Brazil (WC Qualifiers)","is_end_of_season":1,"is_game_day":1,"is_year_anchor":0,"year_anchor_label":"","tournament_finishes":[],"continental_winner":0},{"date":"2022-08-24","rating":-6.197,"rank":60,"conf_rank":13,"last_match":"W 104-98 vs. Brazil (WC Qualifiers)","is_end_of_season":0,"is_game_day":1,"is_year_anchor":0,"year_anchor_label":"","tournament_finishes":[],"continental_winner":0},{"date":"2022-08-25","rating":-1.928,"rank":57,"conf_rank":12,"last_match":"W 93-89 vs. Mexico (WC Qualifiers)","is_end_of_season":0,"is_game_day":1,"is_year_anchor":0,"year_anchor_label":"","tournament_finishes":[],"continental_winner":0},{"date":"2022-08-26","rating":-1.992,"rank":57,"conf_rank":12,"last_match":"W 93-89 vs. Mexico (WC Qualifiers)","is_end_of_season":0,"is_game_day":1,"is_year_anchor":0,"year_anchor_label":"","tournament_finishes":[],"continental_winner":0},{"date":"2022-08-27","rating":-2.046,"rank":57,"conf_rank":12,"last_match":"W 93-89 vs. Mexico (WC Qualifiers)","is_end_of_season":0,"is_game_day":1,"is_year_anchor":0,"year_anchor_label":"","tournament_finishes":[],"continental_winner":0},{"date":"2022-08-28","rating":-1.882,"rank":57,"conf_rank":12,"last_match":"W 93-89 vs. Mexico (WC Qualifiers)","is_end_of_season":0,"is_game_day":1,"is_year_anchor":0,"year_anchor_label":"","tournament_finishes":[],"continental_winner":0},{"date":"2022-08-29","rating":-0.267,"rank":54,"conf_rank":11,"last_match":"L 77-95 vs. United States (WC Qualifiers)","is_end_of_season":0,"is_game_day":1,"is_year_anchor":0,"year_anchor_label":"","tournament_finishes":[],"continental_winner":0},{"date":"2022-08-30","rating":-0.257,"rank":54,"conf_rank":11,"last_match":"L 77-95 vs. United States (WC Qualifiers)","is_end_of_season":0,"is_game_day":1,"is_year_anchor":0,"year_anchor_label":"","tournament_finishes":[],"continental_winner":0},{"date":"2022-09-01","rating":-0.557,"rank":56,"conf_rank":12,"last_match":"L 77-95 vs. United States (WC Qualifiers)","is_end_of_season":0,"is_game_day":1,"is_year_anchor":0,"year_anchor_label":"","tournament_finishes":[],"continental_winner":0},{"date":"2022-09-02","rating":2.323,"rank":42,"conf_rank":11,"last_match":"W 70-64 vs. Uruguay (FIBA AmeriCup)","is_end_of_season":0,"is_game_day":1,"is_year_anchor":0,"year_anchor_label":"","tournament_finishes":[],"continental_winner":0},{"date":"2022-09-03","rating":1.061,"rank":49,"conf_rank":11,"last_match":"L 60-100 vs. Brazil (FIBA AmeriCup)","is_end_of_season":0,"is_game_day":1,"is_year_anchor":0,"year_anchor_label":"","tournament_finishes":[],"continental_winner":0},{"date":"2022-09-04","rating":0.353,"rank":51,"conf_rank":11,"last_match":"L 60-100 vs. Brazil (FIBA AmeriCup)","is_end_of_season":0,"is_game_day":1,"is_year_anchor":0,"year_anchor_label":"","tournament_finishes":[],"continental_winner":0},{"date":"2022-09-05","rating":2.302,"rank":43,"conf_rank":10,"last_match":"L 61-62 vs. Canada (FIBA AmeriCup)","is_end_of_season":0,"is_game_day":1,"is_year_anchor":0,"year_anchor_label":"","tournament_finishes":[],"continental_winner":0},{"date":"2022-09-06","rating":2.433,"rank":43,"conf_rank":10,"last_match":"L 61-62 vs. Canada (FIBA AmeriCup)","is_end_of_season":0,"is_game_day":1,"is_year_anchor":0,"year_anchor_label":"","tournament_finishes":[],"continental_winner":0},{"date":"2022-09-07","rating":2.43,"rank":42,"conf_rank":10,"last_match":"L 61-62 vs. Canada (FIBA AmeriCup)","is_end_of_season":0,"is_game_day":1,"is_year_anchor":0,"year_anchor_label":"","tournament_finishes":[],"continental_winner":0},{"date":"2022-09-08","rating":2.62,"rank":42,"conf_rank":10,"last_match":"L 61-62 vs. Canada (FIBA AmeriCup)","is_end_of_season":0,"is_game_day":1,"is_year_anchor":0,"year_anchor_label":"","tournament_finishes":[],"continental_winner":0},{"date":"2022-09-10","rating":2.645,"rank":42,"conf_rank":10,"last_match":"L 61-62 vs. Canada (FIBA AmeriCup)","is_end_of_season":0,"is_game_day":1,"is_year_anchor":0,"year_anchor_label":"","tournament_finishes":[],"continental_winner":0},{"date":"2022-09-11","rating":2.507,"rank":43,"conf_rank":10,"last_match":"L 61-62 vs. Canada (FIBA AmeriCup)","is_end_of_season":1,"is_game_day":1,"is_year_anchor":1,"year_anchor_label":"End of FIBA AmeriCup","tournament_finishes":[],"continental_winner":0},{"date":"2022-09-13","rating":2.638,"rank":42,"conf_rank":10,"last_match":"L 61-62 vs. Canada (FIBA AmeriCup)","is_end_of_season":0,"is_game_day":1,"is_year_anchor":0,"year_anchor_label":"","tournament_finishes":[],"continental_winner":0},{"date":"2022-09-14","rating":2.753,"rank":42,"conf_rank":10,"last_match":"L 61-62 vs. Canada (FIBA AmeriCup)","is_end_of_season":0,"is_game_day":1,"is_year_anchor":0,"year_anchor_label":"","tournament_finishes":[],"continental_winner":0},{"date":"2022-09-16","rating":2.805,"rank":42,"conf_rank":10,"last_match":"L 61-62 vs. Canada (FIBA AmeriCup)","is_end_of_season":0,"is_game_day":1,"is_year_anchor":0,"year_anchor_label":"","tournament_finishes":[],"continental_winner":0},{"date":"2022-09-18","rating":2.834,"rank":42,"conf_rank":10,"last_match":"L 61-62 vs. Canada (FIBA AmeriCup)","is_end_of_season":1,"is_game_day":1,"is_year_anchor":0,"year_anchor_label":"","tournament_finishes":[],"continental_winner":0},{"date":"2022-11-10","rating":3.332,"rank":41,"conf_rank":10,"last_match":"L 61-62 vs. Canada (FIBA AmeriCup)","is_end_of_season":0,"is_game_day":1,"is_year_anchor":0,"year_anchor_label":"","tournament_finishes":[],"continental_winner":0},{"date":"2022-11-11","rating":3.07,"rank":41,"conf_rank":10,"last_match":"L 79-91 vs. Puerto Rico (WC Qualifiers)","is_end_of_season":0,"is_game_day":1,"is_year_anchor":0,"year_anchor_label":"","tournament_finishes":[],"continental_winner":0},{"date":"2022-11-13","rating":3.222,"rank":41,"conf_rank":10,"last_match":"L 79-91 vs. Puerto Rico (WC Qualifiers)","is_end_of_season":0,"is_game_day":1,"is_year_anchor":0,"year_anchor_label":"","tournament_finishes":[],"continental_winner":0},{"date":"2022-11-14","rating":4.636,"rank":36,"conf_rank":10,"last_match":"L 81-88 vs. United States (WC Qualifiers)","is_end_of_season":0,"is_game_day":1,"is_year_anchor":0,"year_anchor_label":"","tournament_finishes":[],"continental_winner":0}],"2023":[{"date":"2023-02-23","rating":2.644,"rank":40,"conf_rank":10,"last_match":"L 54-113 vs. Mexico (WC Qualifiers)","is_end_of_season":0,"is_game_day":1,"is_year_anchor":0,"year_anchor_label":"","tournament_finishes":[],"continental_winner":0},{"date":"2023-02-24","rating":2.377,"rank":43,"conf_rank":10,"last_match":"L 54-113 vs. Mexico (WC Qualifiers)","is_end_of_season":0,"is_game_day":1,"is_year_anchor":0,"year_anchor_label":"","tournament_finishes":[],"continental_winner":0},{"date":"2023-02-25","rating":2.335,"rank":43,"conf_rank":10,"last_match":"L 54-113 vs. Mexico (WC Qualifiers)","is_end_of_season":0,"is_game_day":1,"is_year_anchor":0,"year_anchor_label":"","tournament_finishes":[],"continental_winner":0},{"date":"2023-02-26","rating":2.311,"rank":44,"conf_rank":10,"last_match":"L 80-87 vs. Puerto Rico (WC Qualifiers)","is_end_of_season":0,"is_game_day":1,"is_year_anchor":0,"year_anchor_label":"","tournament_finishes":[],"continental_winner":0},{"date":"2023-02-27","rating":2.287,"rank":44,"conf_rank":10,"last_match":"L 80-87 vs. Puerto Rico (WC Qualifiers)","is_end_of_season":0,"is_game_day":1,"is_year_anchor":0,"year_anchor_label":"","tournament_finishes":[],"continental_winner":0},{"date":"2023-08-01","rating":2.461,"rank":43,"conf_rank":10,"last_match":"L 80-87 vs. Puerto Rico (WC Qualifiers)","is_end_of_season":0,"is_game_day":1,"is_year_anchor":0,"year_anchor_label":"","tournament_finishes":[],"continental_winner":0},{"date":"2023-08-25","rating":2.45,"rank":40,"conf_rank":10,"last_match":"L 80-87 vs. Puerto Rico (WC Qualifiers)","is_end_of_season":0,"is_game_day":1,"is_year_anchor":0,"year_anchor_label":"","tournament_finishes":[],"continental_winner":0},{"date":"2023-08-26","rating":3.381,"rank":38,"conf_rank":10,"last_match":"L 80-87 vs. Puerto Rico (WC Qualifiers)","is_end_of_season":0,"is_game_day":1,"is_year_anchor":0,"year_anchor_label":"","tournament_finishes":[],"continental_winner":0},{"date":"2023-08-27","rating":3.074,"rank":38,"conf_rank":10,"last_match":"L 80-87 vs. Puerto Rico (WC Qualifiers)","is_end_of_season":0,"is_game_day":1,"is_year_anchor":0,"year_anchor_label":"","tournament_finishes":[],"continental_winner":0},{"date":"2023-08-28","rating":2.062,"rank":44,"conf_rank":10,"last_match":"L 80-87 vs. Puerto Rico (WC Qualifiers)","is_end_of_season":0,"is_game_day":1,"is_year_anchor":0,"year_anchor_label":"","tournament_finishes":[],"continental_winner":0},{"date":"2023-08-29","rating":1.411,"rank":46,"conf_rank":10,"last_match":"L 80-87 vs. Puerto Rico (WC Qualifiers)","is_end_of_season":0,"is_game_day":1,"is_year_anchor":0,"year_anchor_label":"","tournament_finishes":[],"continental_winner":0},{"date":"2023-08-30","rating":1.539,"rank":46,"conf_rank":10,"last_match":"L 80-87 vs. Puerto Rico (WC Qualifiers)","is_end_of_season":0,"is_game_day":1,"is_year_anchor":0,"year_anchor_label":"","tournament_finishes":[],"continental_winner":0},{"date":"2023-08-31","rating":1.771,"rank":45,"conf_rank":10,"last_match":"L 80-87 vs. Puerto Rico (WC Qualifiers)","is_end_of_season":0,"is_game_day":1,"is_year_anchor":0,"year_anchor_label":"","tournament_finishes":[],"continental_winner":0},{"date":"2023-09-01","rating":2.15,"rank":45,"conf_rank":10,"last_match":"L 80-87 vs. Puerto Rico (WC Qualifiers)","is_end_of_season":0,"is_game_day":1,"is_year_anchor":0,"year_anchor_label":"","tournament_finishes":[],"continental_winner":0},{"date":"2023-09-02","rating":2.18,"rank":42,"conf_rank":9,"last_match":"L 80-87 vs. Puerto Rico (WC Qualifiers)","is_end_of_season":0,"is_game_day":1,"is_year_anchor":0,"year_anchor_label":"","tournament_finishes":[],"continental_winner":0},{"date":"2023-09-03","rating":1.188,"rank":45,"conf_rank":10,"last_match":"L 80-87 vs. Puerto Rico (WC Qualifiers)","is_end_of_season":0,"is_game_day":1,"is_year_anchor":0,"year_anchor_label":"","tournament_finishes":[],"continental_winner":0},{"date":"2023-09-05","rating":1.373,"rank":44,"conf_rank":10,"last_match":"L 80-87 vs. Puerto Rico (WC Qualifiers)","is_end_of_season":0,"is_game_day":1,"is_year_anchor":0,"year_anchor_label":"","tournament_finishes":[],"continental_winner":0},{"date":"2023-09-06","rating":1.508,"rank":44,"conf_rank":10,"last_match":"L 80-87 vs. Puerto Rico (WC Qualifiers)","is_end_of_season":0,"is_game_day":1,"is_year_anchor":0,"year_anchor_label":"","tournament_finishes":[],"continental_winner":0},{"date":"2023-09-07","rating":1.699,"rank":43,"conf_rank":9,"last_match":"L 80-87 vs. Puerto Rico (WC Qualifiers)","is_end_of_season":0,"is_game_day":1,"is_year_anchor":0,"year_anchor_label":"","tournament_finishes":[],"continental_winner":0},{"date":"2023-09-08","rating":1.552,"rank":43,"conf_rank":9,"last_match":"L 80-87 vs. Puerto Rico (WC Qualifiers)","is_end_of_season":0,"is_game_day":1,"is_year_anchor":0,"year_anchor_label":"","tournament_finishes":[],"continental_winner":0},{"date":"2023-09-09","rating":1.611,"rank":43,"conf_rank":9,"last_match":"L 80-87 vs. Puerto Rico (WC Qualifiers)","is_end_of_season":0,"is_game_day":1,"is_year_anchor":0,"year_anchor_label":"","tournament_finishes":[],"continental_winner":0},{"date":"2023-09-10","rating":1.58,"rank":43,"conf_rank":9,"last_match":"L 80-87 vs. Puerto Rico (WC Qualifiers)","is_end_of_season":1,"is_game_day":1,"is_year_anchor":1,"year_anchor_label":"End of year","tournament_finishes":[],"continental_winner":0}],"2024":[{"date":"2024-07-27","rating":0.844,"rank":46,"conf_rank":10,"last_match":"L 80-87 vs. Puerto Rico (WC Qualifiers)","is_end_of_season":0,"is_game_day":1,"is_year_anchor":0,"year_anchor_label":"","tournament_finishes":[],"continental_winner":0},{"date":"2024-07-28","rating":1.208,"rank":44,"conf_rank":9,"last_match":"L 80-87 vs. Puerto Rico (WC Qualifiers)","is_end_of_season":0,"is_game_day":1,"is_year_anchor":0,"year_anchor_label":"","tournament_finishes":[],"continental_winner":0},{"date":"2024-07-30","rating":0.962,"rank":45,"conf_rank":10,"last_match":"L 80-87 vs. Puerto Rico (WC Qualifiers)","is_end_of_season":0,"is_game_day":1,"is_year_anchor":0,"year_anchor_label":"","tournament_finishes":[],"continental_winner":0},{"date":"2024-07-31","rating":0.642,"rank":45,"conf_rank":10,"last_match":"L 80-87 vs. Puerto Rico (WC Qualifiers)","is_end_of_season":0,"is_game_day":1,"is_year_anchor":0,"year_anchor_label":"","tournament_finishes":[],"continental_winner":0},{"date":"2024-08-02","rating":1.097,"rank":44,"conf_rank":10,"last_match":"L 80-87 vs. Puerto Rico (WC Qualifiers)","is_end_of_season":0,"is_game_day":1,"is_year_anchor":0,"year_anchor_label":"","tournament_finishes":[],"continental_winner":0},{"date":"2024-08-03","rating":1.09,"rank":44,"conf_rank":10,"last_match":"L 80-87 vs. Puerto Rico (WC Qualifiers)","is_end_of_season":0,"is_game_day":1,"is_year_anchor":0,"year_anchor_label":"","tournament_finishes":[],"continental_winner":0},{"date":"2024-08-06","rating":0.706,"rank":46,"conf_rank":10,"last_match":"L 80-87 vs. Puerto Rico (WC Qualifiers)","is_end_of_season":0,"is_game_day":1,"is_year_anchor":0,"year_anchor_label":"","tournament_finishes":[],"continental_winner":0},{"date":"2024-08-08","rating":0.703,"rank":46,"conf_rank":10,"last_match":"L 80-87 vs. Puerto Rico (WC Qualifiers)","is_end_of_season":0,"is_game_day":1,"is_year_anchor":0,"year_anchor_label":"","tournament_finishes":[],"continental_winner":0},{"date":"2024-08-10","rating":0.845,"rank":46,"conf_rank":10,"last_match":"L 80-87 vs. Puerto Rico (WC Qualifiers)","is_end_of_season":1,"is_game_day":1,"is_year_anchor":1,"year_anchor_label":"End of year","tournament_finishes":[],"continental_winner":0}],"2025":[{"date":"2025-08-05","rating":-0.976,"rank":43,"conf_rank":10,"last_match":"L 80-87 vs. Puerto Rico (WC Qualifiers)","is_end_of_season":0,"is_game_day":1,"is_year_anchor":0,"year_anchor_label":"","tournament_finishes":[],"continental_winner":0},{"date":"2025-08-06","rating":-0.491,"rank":43,"conf_rank":10,"last_match":"L 80-87 vs. Puerto Rico (WC Qualifiers)","is_end_of_season":0,"is_game_day":1,"is_year_anchor":0,"year_anchor_label":"","tournament_finishes":[],"continental_winner":0},{"date":"2025-08-07","rating":-0.504,"rank":43,"conf_rank":10,"last_match":"L 80-87 vs. Puerto Rico (WC Qualifiers)","is_end_of_season":0,"is_game_day":1,"is_year_anchor":0,"year_anchor_label":"","tournament_finishes":[],"continental_winner":0},{"date":"2025-08-08","rating":-0.579,"rank":43,"conf_rank":10,"last_match":"L 80-87 vs. Puerto Rico (WC Qualifiers)","is_end_of_season":0,"is_game_day":1,"is_year_anchor":0,"year_anchor_label":"","tournament_finishes":[],"continental_winner":0},{"date":"2025-08-09","rating":-0.576,"rank":43,"conf_rank":10,"last_match":"L 80-87 vs. Puerto Rico (WC Qualifiers)","is_end_of_season":0,"is_game_day":1,"is_year_anchor":0,"year_anchor_label":"","tournament_finishes":[],"continental_winner":0},{"date":"2025-08-10","rating":-0.599,"rank":44,"conf_rank":10,"last_match":"L 80-87 vs. Puerto Rico (WC Qualifiers)","is_end_of_season":0,"is_game_day":1,"is_year_anchor":0,"year_anchor_label":"","tournament_finishes":[],"continental_winner":0},{"date":"2025-08-11","rating":-0.662,"rank":44,"conf_rank":10,"last_match":"L 80-87 vs. Puerto Rico (WC Qualifiers)","is_end_of_season":0,"is_game_day":1,"is_year_anchor":0,"year_anchor_label":"","tournament_finishes":[],"continental_winner":0},{"date":"2025-08-12","rating":-0.984,"rank":45,"conf_rank":10,"last_match":"L 80-87 vs. Puerto Rico (WC Qualifiers)","is_end_of_season":0,"is_game_day":1,"is_year_anchor":0,"year_anchor_label":"","tournament_finishes":[],"continental_winner":0},{"date":"2025-08-13","rating":-0.69,"rank":45,"conf_rank":10,"last_match":"L 80-87 vs. Puerto Rico (WC Qualifiers)","is_end_of_season":0,"is_game_day":1,"is_year_anchor":0,"year_anchor_label":"","tournament_finishes":[],"continental_winner":0},{"date":"2025-08-14","rating":-0.622,"rank":47,"conf_rank":10,"last_match":"L 80-87 vs. Puerto Rico (WC Qualifiers)","is_end_of_season":0,"is_game_day":1,"is_year_anchor":0,"year_anchor_label":"","tournament_finishes":[],"continental_winner":0},{"date":"2025-08-15","rating":-0.813,"rank":47,"conf_rank":10,"last_match":"L 80-87 vs. Puerto Rico (WC Qualifiers)","is_end_of_season":0,"is_game_day":1,"is_year_anchor":0,"year_anchor_label":"","tournament_finishes":[],"continental_winner":0},{"date":"2025-08-16","rating":-0.995,"rank":48,"conf_rank":10,"last_match":"L 80-87 vs. Puerto Rico (WC Qualifiers)","is_end_of_season":0,"is_game_day":1,"is_year_anchor":0,"year_anchor_label":"","tournament_finishes":[],"continental_winner":0},{"date":"2025-08-17","rating":-0.923,"rank":48,"conf_rank":10,"last_match":"L 80-87 vs. Puerto Rico (WC Qualifiers)","is_end_of_season":1,"is_game_day":1,"is_year_anchor":0,"year_anchor_label":"","tournament_finishes":[],"continental_winner":0},{"date":"2025-08-18","rating":-1.147,"rank":48,"conf_rank":10,"last_match":"L 80-87 vs. Puerto Rico (WC Qualifiers)","is_end_of_season":0,"is_game_day":1,"is_year_anchor":0,"year_anchor_label":"","tournament_finishes":[],"continental_winner":0},{"date":"2025-08-19","rating":-1.065,"rank":48,"conf_rank":10,"last_match":"L 80-87 vs. Puerto Rico (WC Qualifiers)","is_end_of_season":0,"is_game_day":1,"is_year_anchor":0,"year_anchor_label":"","tournament_finishes":[],"continental_winner":0},{"date":"2025-08-20","rating":-1.07,"rank":48,"conf_rank":10,"last_match":"L 80-87 vs. Puerto Rico (WC Qualifiers)","is_end_of_season":0,"is_game_day":1,"is_year_anchor":0,"year_anchor_label":"","tournament_finishes":[],"continental_winner":0},{"date":"2025-08-21","rating":-1.292,"rank":49,"conf_rank":10,"last_match":"L 80-87 vs. Puerto Rico (WC Qualifiers)","is_end_of_season":0,"is_game_day":1,"is_year_anchor":0,"year_anchor_label":"","tournament_finishes":[],"continental_winner":0},{"date":"2025-08-22","rating":-5.633,"rank":59,"conf_rank":11,"last_match":"L 59-84 vs. Dominican Republic (FIBA AmeriCup)","is_end_of_season":0,"is_game_day":1,"is_year_anchor":0,"year_anchor_label":"","tournament_finishes":[],"continental_winner":0},{"date":"2025-08-23","rating":-5.252,"rank":59,"conf_rank":12,"last_match":"L 59-84 vs. Dominican Republic (FIBA AmeriCup)","is_end_of_season":0,"is_game_day":1,"is_year_anchor":0,"year_anchor_label":"","tournament_finishes":[],"continental_winner":0},{"date":"2025-08-24","rating":-4.882,"rank":60,"conf_rank":13,"last_match":"W 89-86 vs. Nicaragua (FIBA AmeriCup)","is_end_of_season":1,"is_game_day":1,"is_year_anchor":0,"year_anchor_label":"","tournament_finishes":[],"continental_winner":0},{"date":"2025-08-25","rating":-1.71,"rank":49,"conf_rank":10,"last_match":"L 83-84 vs. Argentina (FIBA AmeriCup)","is_end_of_season":0,"is_game_day":1,"is_year_anchor":0,"year_anchor_label":"","tournament_finishes":[],"continental_winner":0},{"date":"2025-08-26","rating":-1.677,"rank":48,"conf_rank":10,"last_match":"L 83-84 vs. Argentina (FIBA AmeriCup)","is_end_of_season":0,"is_game_day":1,"is_year_anchor":0,"year_anchor_label":"","tournament_finishes":[],"continental_winner":0},{"date":"2025-08-27","rating":-1.724,"rank":50,"conf_rank":10,"last_match":"L 83-84 vs. Argentina (FIBA AmeriCup)","is_end_of_season":0,"is_game_day":1,"is_year_anchor":0,"year_anchor_label":"","tournament_finishes":[],"continental_winner":0},{"date":"2025-08-28","rating":-2.359,"rank":51,"conf_rank":10,"last_match":"L 56-94 vs. Canada (FIBA AmeriCup)","is_end_of_season":0,"is_game_day":1,"is_year_anchor":0,"year_anchor_label":"","tournament_finishes":[],"continental_winner":0},{"date":"2025-08-29","rating":-2.362,"rank":51,"conf_rank":10,"last_match":"L 56-94 vs. Canada (FIBA AmeriCup)","is_end_of_season":0,"is_game_day":1,"is_year_anchor":0,"year_anchor_label":"","tournament_finishes":[],"continental_winner":0},{"date":"2025-08-30","rating":-1.633,"rank":50,"conf_rank":10,"last_match":"L 56-94 vs. Canada (FIBA AmeriCup)","is_end_of_season":0,"is_game_day":1,"is_year_anchor":0,"year_anchor_label":"","tournament_finishes":[],"continental_winner":0},{"date":"2025-08-31","rating":-1.83,"rank":50,"conf_rank":10,"last_match":"L 56-94 vs. Canada (FIBA AmeriCup)","is_end_of_season":1,"is_game_day":1,"is_year_anchor":1,"year_anchor_label":"End of FIBA AmeriCup","tournament_finishes":[],"continental_winner":0},{"date":"2025-09-01","rating":-1.841,"rank":50,"conf_rank":10,"last_match":"L 56-94 vs. Canada (FIBA AmeriCup)","is_end_of_season":0,"is_game_day":1,"is_year_anchor":0,"year_anchor_label":"","tournament_finishes":[],"continental_winner":0},{"date":"2025-09-02","rating":-1.813,"rank":50,"conf_rank":10,"last_match":"L 56-94 vs. Canada (FIBA AmeriCup)","is_end_of_season":0,"is_game_day":1,"is_year_anchor":0,"year_anchor_label":"","tournament_finishes":[],"continental_winner":0},{"date":"2025-09-03","rating":-1.839,"rank":50,"conf_rank":10,"last_match":"L 56-94 vs. Canada (FIBA AmeriCup)","is_end_of_season":0,"is_game_day":1,"is_year_anchor":0,"year_anchor_label":"","tournament_finishes":[],"continental_winner":0},{"date":"2025-09-04","rating":-1.78,"rank":49,"conf_rank":10,"last_match":"L 56-94 vs. Canada (FIBA AmeriCup)","is_end_of_season":0,"is_game_day":1,"is_year_anchor":0,"year_anchor_label":"","tournament_finishes":[],"continental_winner":0},{"date":"2025-09-06","rating":-1.851,"rank":50,"conf_rank":10,"last_match":"L 56-94 vs. Canada (FIBA AmeriCup)","is_end_of_season":0,"is_game_day":1,"is_year_anchor":0,"year_anchor_label":"","tournament_finishes":[],"continental_winner":0},{"date":"2025-09-07","rating":-1.957,"rank":51,"conf_rank":10,"last_match":"L 56-94 vs. Canada (FIBA AmeriCup)","is_end_of_season":0,"is_game_day":1,"is_year_anchor":0,"year_anchor_label":"","tournament_finishes":[],"continental_winner":0},{"date":"2025-09-09","rating":-1.944,"rank":51,"conf_rank":10,"last_match":"L 56-94 vs. Canada (FIBA AmeriCup)","is_end_of_season":0,"is_game_day":1,"is_year_anchor":0,"year_anchor_label":"","tournament_finishes":[],"continental_winner":0},{"date":"2025-09-10","rating":-1.952,"rank":51,"conf_rank":10,"last_match":"L 56-94 vs. Canada (FIBA AmeriCup)","is_end_of_season":0,"is_game_day":1,"is_year_anchor":0,"year_anchor_label":"","tournament_finishes":[],"continental_winner":0},{"date":"2025-09-12","rating":-2.008,"rank":51,"conf_rank":10,"last_match":"L 56-94 vs. Canada (FIBA AmeriCup)","is_end_of_season":0,"is_game_day":1,"is_year_anchor":0,"year_anchor_label":"","tournament_finishes":[],"continental_winner":0},{"date":"2025-09-14","rating":-2.002,"rank":51,"conf_rank":10,"last_match":"L 56-94 vs. Canada (FIBA AmeriCup)","is_end_of_season":1,"is_game_day":1,"is_year_anchor":0,"year_anchor_label":"","tournament_finishes":[],"continental_winner":0}]}}